[
  {
    "slug": "erie-gold-exchange",
    "citySlug": "erie",
    "name": "Erie Gold Exchange",
    "phone": "+1 814-878-0003",
    "website": "http://www.eriegoldexchange.com/",
    "address": "2256 W 8th St, Erie, PA 16505",
    "street": "2256 W 8th St",
    "city": "Erie",
    "state": "Pennsylvania",
    "zip": "16505",
    "rating": 4.9,
    "reviews": 648,
    "hours": "{\"Monday\": [\"9:30AM-5PM\"], \"Tuesday\": [\"9:30AM-5PM\"], \"Wednesday\": [\"9:30AM-5PM\"], \"Thursday\": [\"9:30AM-5PM\"], \"Friday\": [\"9:30AM-5PM\"], \"Saturday\": [\"9:30AM-4PM\"], \"Sunday\": [\"Closed\"]}",
    "latitude": 42.10880909999999,
    "longitude": -80.1356271,
    "placeId": "ChIJ7xFX4Zh_MogRcGbYzWIqcCU",
    "googleMapsUrl": null
  },
  {
    "slug": "erie-gold-exchange",
    "citySlug": "erie",
    "name": "Erie Gold Exchange",
    "phone": "+1 814-864-0028",
    "website": "http://www.eriegoldexchange.com/",
    "address": "5034 Peach St, Erie, PA 16509",
    "street": "5034 Peach St",
    "city": "Erie",
    "state": "Pennsylvania",
    "zip": "16509",
    "rating": 4.9,
    "reviews": 543,
    "hours": "{\"Monday\": [\"9:30AM-5PM\"], \"Tuesday\": [\"9:30AM-5PM\"], \"Wednesday\": [\"9:30AM-5PM\"], \"Thursday\": [\"9:30AM-5PM\"], \"Friday\": [\"9:30AM-5PM\"], \"Saturday\": [\"9:30AM-4PM\"], \"Sunday\": [\"Closed\"]}",
    "latitude": 42.0804633,
    "longitude": -80.0911465,
    "placeId": "ChIJWeRcHYeAMogRG30XixNuq6o",
    "googleMapsUrl": null
  },
  {
    "slug": "we-buy-everything-pawn-shop-springfield",
    "citySlug": "springfield",
    "name": "We Buy Everything Pawn Shop - Springfield",
    "phone": "+1 610-604-4445",
    "website": "http://www.webuyeverything.com/",
    "address": "156 Baltimore Pike, Springfield, PA 19064",
    "street": "156 Baltimore Pike",
    "city": "Springfield",
    "state": "Pennsylvania",
    "zip": "19064",
    "rating": 4.5,
    "reviews": 739,
    "hours": "{\"Monday\": [\"10AM-6PM\"], \"Tuesday\": [\"10AM-6PM\"], \"Wednesday\": [\"10AM-6PM\"], \"Thursday\": [\"10AM-6PM\"], \"Friday\": [\"10AM-6PM\"], \"Saturday\": [\"10AM-4PM\"], \"Sunday\": [\"10AM-3PM\"]}",
    "latitude": 39.9235938,
    "longitude": -75.31642599999999,
    "placeId": "ChIJ3_UgsQzDxokRbWFYz4Jp5Qk",
    "googleMapsUrl": null
  },
  {
    "slug": "bayfront-entertainment",
    "citySlug": "erie",
    "name": "Bayfront Entertainment",
    "phone": "+1 814-520-7563",
    "website": "http://www.bayfront-entertainment.com/",
    "address": "1210 W 26th St, Erie, PA 16508",
    "street": "1210 W 26th St",
    "city": "Erie",
    "state": "Pennsylvania",
    "zip": "16508",
    "rating": 4.1,
    "reviews": 161,
    "hours": "{\"Monday\": [\"12-7PM\"], \"Tuesday\": [\"12-7PM\"], \"Wednesday\": [\"12-7PM\"], \"Thursday\": [\"12-7PM\"], \"Friday\": [\"12-9PM\"], \"Saturday\": [\"12-8PM\"], \"Sunday\": [\"Closed\"]}",
    "latitude": 42.1024994,
    "longitude": -80.09964939999999,
    "placeId": "ChIJt0OcBdt_LYgRbk1gHLZP1RQ",
    "googleMapsUrl": null
  },
  {
    "slug": "loucks-pawn-shop",
    "citySlug": "erie",
    "name": "LOUCKS PAWN SHOP",
    "phone": "+1 814-520-7563",
    "website": "http://www.louckspawnshop.webs.com/",
    "address": "Holland St, Erie, PA 16503",
    "street": "Holland St",
    "city": "Erie",
    "state": "Pennsylvania",
    "zip": "16503",
    "rating": null,
    "reviews": null,
    "hours": null,
    "latitude": 42.1209544,
    "longitude": -80.0748461,
    "placeId": "ChIJtWs67uZ_LYgRztRb2HgVmh0",
    "googleMapsUrl": null
  },
  {
    "slug": "vintage-vibes-buy-sell-trade",
    "citySlug": "harrisburg",
    "name": "Vintage Vibes Buy Sell Trade",
    "phone": "+1 717-383-7296",
    "website": "https://vintageharrisburg.company.site/",
    "address": "1003 N 3rd St, Harrisburg, PA 17102",
    "street": "1003 N 3rd St",
    "city": "Harrisburg",
    "state": "Pennsylvania",
    "zip": "17102",
    "rating": 5,
    "reviews": 26,
    "hours": "{\"Monday\": [\"11AM-6PM\"], \"Tuesday\": [\"11AM-5PM\"], \"Wednesday\": [\"11AM-6PM\"], \"Thursday\": [\"11AM-6PM\"], \"Friday\": [\"11AM-6PM\"], \"Saturday\": [\"12-6PM\"], \"Sunday\": [\"12-5PM\"]}",
    "latitude": 40.2676076,
    "longitude": -76.8872675,
    "placeId": "ChIJgePXwgbByIkR8cE5VYJYlPQ",
    "googleMapsUrl": null
  },
  {
    "slug": "top-cash-paid",
    "citySlug": "harrisburg",
    "name": "Top Cash Paid",
    "phone": "+1 717-460-0099",
    "website": "https://www.topcashpaid24-7.com/",
    "address": "3405 Walnut St, Harrisburg, PA 17109",
    "street": "3405 Walnut St",
    "city": "Harrisburg",
    "state": "Pennsylvania",
    "zip": "17109",
    "rating": 4.6,
    "reviews": 322,
    "hours": "{\"Monday\": [\"Open 24 hours\"], \"Tuesday\": [\"Open 24 hours\"], \"Wednesday\": [\"Open 24 hours\"], \"Thursday\": [\"Open 24 hours\"], \"Friday\": [\"Open 24 hours\"], \"Saturday\": [\"Open 24 hours\"], \"Sunday\": [\"Open 24 hours\"]}",
    "latitude": 40.2853239,
    "longitude": -76.8406682,
    "placeId": "ChIJDS30KLPAyIkR2XhZOBhK6qw",
    "googleMapsUrl": null
  },
  {
    "slug": "capitol-city-buy-sell-pawn",
    "citySlug": "harrisburg",
    "name": "CAPITOL CITY BUY • SELL • PAWN",
    "phone": "+1 717-409-8597",
    "website": "http://harrisburgpapawn.com/",
    "address": "3517 Walnut St, Harrisburg, PA 17109",
    "street": "3517 Walnut St",
    "city": "Harrisburg",
    "state": "Pennsylvania",
    "zip": "17109",
    "rating": 4.7,
    "reviews": 670,
    "hours": "{\"Monday\": [\"9AM-5PM\"], \"Tuesday\": [\"9AM-5PM\"], \"Wednesday\": [\"9AM-5PM\"], \"Thursday\": [\"9AM-5PM\"], \"Friday\": [\"9AM-5PM\"], \"Saturday\": [\"9AM-5PM\"], \"Sunday\": [\"Closed\"]}",
    "latitude": 40.2871253,
    "longitude": -76.8382772,
    "placeId": "ChIJu_NMb03HyIkRl2Os7a4Uicw",
    "googleMapsUrl": null
  },
  {
    "slug": "simple-gold-exchange-cash-for-gold-silver-and-gold-coins",
    "citySlug": "harrisburg",
    "name": "Simple Gold Exchange - CASH FOR GOLD SILVER AND GOLD COINS",
    "phone": "+1 484-363-9252",
    "website": "https://www.facebook.com/pg/simplegoldexchange/photos/%3Fref%3Dpage_internal",
    "address": "4600 Jonestown Rd, Harrisburg, PA 17109",
    "street": "4600 Jonestown Rd",
    "city": "Harrisburg",
    "state": "Pennsylvania",
    "zip": "17109",
    "rating": 4.1,
    "reviews": 63,
    "hours": "{\"Monday\": [\"10AM-8PM\"], \"Tuesday\": [\"10AM-8PM\"], \"Wednesday\": [\"10AM-8PM\"], \"Thursday\": [\"10AM-8PM\"], \"Friday\": [\"10AM-8PM\"], \"Saturday\": [\"10AM-8PM\"], \"Sunday\": [\"12-6PM\"]}",
    "latitude": 40.302399,
    "longitude": -76.8190815,
    "placeId": "ChIJTXxJN5S4yIkR83ezRSNtk4I",
    "googleMapsUrl": null
  },
  {
    "slug": "national-jewelry-and-pawn",
    "citySlug": "harrisburg",
    "name": "National Jewelry and Pawn",
    "phone": "+1 717-963-8530",
    "website": "https://www.nationaljewelryandpawn.com/",
    "address": "2900 Herr St, Harrisburg, PA 17103",
    "street": "2900 Herr St",
    "city": "Harrisburg",
    "state": "Pennsylvania",
    "zip": "17103",
    "rating": 4.6,
    "reviews": 125,
    "hours": "{\"Monday\": [\"9:30AM-5PM\"], \"Tuesday\": [\"9:30AM-5PM\"], \"Wednesday\": [\"9:30AM-5PM\"], \"Thursday\": [\"9:30AM-5PM\"], \"Friday\": [\"9:30AM-5PM\"], \"Saturday\": [\"9:30AM-5PM\"], \"Sunday\": [\"Closed\"]}",
    "latitude": 40.2823407,
    "longitude": -76.8462129,
    "placeId": "ChIJ53yK8gvByIkRfmi3M-06Gxs",
    "googleMapsUrl": null
  },
  {
    "slug": "capitol-city-buy-sell-pawn",
    "citySlug": "mechanicsburg",
    "name": "CAPITOL CITY BUY SELL PAWN",
    "phone": "+1 717-550-2872",
    "website": "http://capitolcitybuysellpawn.com/",
    "address": "5223 Simpson Ferry Rd, Mechanicsburg, PA 17050",
    "street": "5223 Simpson Ferry Rd",
    "city": "Mechanicsburg",
    "state": "Pennsylvania",
    "zip": "17050",
    "rating": 4.8,
    "reviews": 482,
    "hours": "{\"Monday\": [\"9AM-5PM\"], \"Tuesday\": [\"9AM-5PM\"], \"Wednesday\": [\"9AM-5PM\"], \"Thursday\": [\"9AM-5PM\"], \"Friday\": [\"9AM-5PM\"], \"Saturday\": [\"9AM-5PM\"], \"Sunday\": [\"Closed\"]}",
    "latitude": 40.2182144,
    "longitude": -76.98199269999999,
    "placeId": "ChIJ2_61ex_pyIkR05jGQS8__RY",
    "googleMapsUrl": null
  },
  {
    "slug": "capitol-city-buy-sell-pawn",
    "citySlug": "grantville",
    "name": "CAPITOL CITY BUY • SELL • PAWN",
    "phone": "+1 717-469-4068",
    "website": "https://capitolcitybuysellpawn.com/",
    "address": "545 Bow Creek Rd, Grantville, PA 17028",
    "street": "545 Bow Creek Rd",
    "city": "Grantville",
    "state": "Pennsylvania",
    "zip": "17028",
    "rating": 4.9,
    "reviews": 222,
    "hours": "{\"Monday\": [\"Closed\"], \"Tuesday\": [\"9AM-5PM\"], \"Wednesday\": [\"9AM-5PM\"], \"Thursday\": [\"9AM-5PM\"], \"Friday\": [\"9AM-5PM\"], \"Saturday\": [\"9AM-5PM\"], \"Sunday\": [\"Closed\"]}",
    "latitude": 40.384379,
    "longitude": -76.66516229999999,
    "placeId": "ChIJLU_AmXSxyIkRUIlZSWpFZMs",
    "googleMapsUrl": null
  },
  {
    "slug": "chicos-counter-buy-and-sell",
    "citySlug": "harrisburg",
    "name": "Chico's Counter Buy And Sell",
    "phone": "+1 717-455-7175",
    "website": "https://chicoscounterbuyandsell.com/",
    "address": "109 N 2nd St, Harrisburg, PA 17101",
    "street": "109 N 2nd St",
    "city": "Harrisburg",
    "state": "Pennsylvania",
    "zip": "17101",
    "rating": 4.7,
    "reviews": 11,
    "hours": "{\"Monday\": [\"9AM-5PM\"], \"Tuesday\": [\"9AM-5PM\"], \"Wednesday\": [\"9AM-5PM\"], \"Thursday\": [\"9AM-5PM\"], \"Friday\": [\"9AM-5PM\"], \"Saturday\": [\"9AM-2PM\"], \"Sunday\": [\"Closed\"]}",
    "latitude": 40.2608523,
    "longitude": -76.88355349999999,
    "placeId": "ChIJcd4z4L7ByIkRc37iBnXjyTY",
    "googleMapsUrl": null
  },
  {
    "slug": "adams-county-gold-silver-and-coin-exchange",
    "citySlug": "littlestown",
    "name": "Adams County Gold, Silver and Coin Exchange",
    "phone": "+1 410-259-4789",
    "website": "https://www.ebay.com/sch/adams_county_gold/m.html%3F_nkw%3D%26_armrs%3D1%26_ipg%3D%26_from%3D",
    "address": "2 E King St Rear, Littlestown, PA 17340",
    "street": "2 E King St Rear",
    "city": "Littlestown",
    "state": "Pennsylvania",
    "zip": "17340",
    "rating": 1.8,
    "reviews": 15,
    "hours": "{\"Monday\": [\"10AM-5PM\"], \"Tuesday\": [\"10AM-5PM\"], \"Wednesday\": [\"10AM-5PM\"], \"Thursday\": [\"10AM-5PM\"], \"Friday\": [\"10AM-5PM\"], \"Saturday\": [\"10AM-4PM\"], \"Sunday\": [\"12-3PM\"]}",
    "latitude": 39.74489639999999,
    "longitude": -77.0881449,
    "placeId": "ChIJ4VU_ihxOyIkRFZ25LhnMbPg",
    "googleMapsUrl": null
  },
  {
    "slug": "fair-trade-outlet",
    "citySlug": "irwin",
    "name": "Fair Trade Outlet",
    "phone": "+1 724-863-4444",
    "website": "https://fairtradeoutlet.com/",
    "address": "10719 US-30, Irwin, PA 15642",
    "street": "10719 US-30",
    "city": "Irwin",
    "state": "Pennsylvania",
    "zip": "15642",
    "rating": 4.8,
    "reviews": 44,
    "hours": "{\"Monday\": [\"10AM-5PM\"], \"Tuesday\": [\"10AM-5PM\"], \"Wednesday\": [\"10AM-5PM\"], \"Thursday\": [\"10AM-5PM\"], \"Friday\": [\"10AM-5PM\"], \"Saturday\": [\"10AM-4PM\"], \"Sunday\": [\"Closed\"]}",
    "latitude": 40.3279136,
    "longitude": -79.72131879999999,
    "placeId": "ChIJP-xiOUbdNIgRAin_Czou1pc",
    "googleMapsUrl": null
  },
  {
    "slug": "pawn-shop-philadelphia",
    "citySlug": "philadelphia",
    "name": "Pawn Shop Philadelphia",
    "phone": "+1 267-687-2640",
    "website": "http://pawnshopphiladelphia.com/",
    "address": "136 S 8th St, Philadelphia, PA 19107",
    "street": "136 S 8th St",
    "city": "Philadelphia",
    "state": "Pennsylvania",
    "zip": "19107",
    "rating": 4.5,
    "reviews": 74,
    "hours": "{\"Monday\": [\"10:30AM-5:30PM\"], \"Tuesday\": [\"10:30AM-5:30PM\"], \"Wednesday\": [\"10:30AM-5:30PM\"], \"Thursday\": [\"10:30AM-5:30PM\"], \"Friday\": [\"10:30AM-5:30PM\"], \"Saturday\": [\"Closed\"], \"Sunday\": [\"Closed\"]}",
    "latitude": 39.948392,
    "longitude": -75.1543739,
    "placeId": "ChIJMXShqYLIxokR-9J4VX-CUXo",
    "googleMapsUrl": null
  },
  {
    "slug": "the-pawn-jewelry-exchange",
    "citySlug": "greensburg",
    "name": "The Pawn & Jewelry Exchange",
    "phone": "+1 724-836-7296",
    "website": "https://www.pawnshopgreensburgpa.com/",
    "address": "206 E Pittsburgh St, Greensburg, PA 15601",
    "street": "206 E Pittsburgh St",
    "city": "Greensburg",
    "state": "Pennsylvania",
    "zip": "15601",
    "rating": 4.4,
    "reviews": 161,
    "hours": "{\"Monday\": [\"9AM-6PM\"], \"Tuesday\": [\"9AM-6PM\"], \"Wednesday\": [\"9AM-6PM\"], \"Thursday\": [\"9AM-6PM\"], \"Friday\": [\"9AM-6PM\"], \"Saturday\": [\"9AM-12PM\"], \"Sunday\": [\"Closed\"]}",
    "latitude": 40.303083,
    "longitude": -79.5404089,
    "placeId": "ChIJ5zGm7jjQNIgRsDewFwTwiQk",
    "googleMapsUrl": null
  },
  {
    "slug": "gold-rush-pittsburgh",
    "citySlug": "pittsburgh",
    "name": "Gold Rush Pittsburgh",
    "phone": "+1 412-224-2938",
    "website": "https://goldrushco.com/",
    "address": "4705 Liberty Ave, Pittsburgh, PA 15224",
    "street": "4705 Liberty Ave",
    "city": "Pittsburgh",
    "state": "Pennsylvania",
    "zip": "15224",
    "rating": 4.9,
    "reviews": 456,
    "hours": "{\"Monday\": [\"10AM-7PM\"], \"Tuesday\": [\"10AM-7PM\"], \"Wednesday\": [\"10AM-7PM\"], \"Thursday\": [\"10AM-7PM\"], \"Friday\": [\"10AM-7PM\"], \"Saturday\": [\"10AM-7PM\"], \"Sunday\": [\"11AM-6PM\"]}",
    "latitude": 40.4621274,
    "longitude": -79.9496106,
    "placeId": "ChIJnci1BUfyNIgRrZdZP_44Ssw",
    "googleMapsUrl": null
  },
  {
    "slug": "forgys-speed-sports-sales",
    "citySlug": "duncansville",
    "name": "Forgy's Speed & Sports Sales",
    "phone": "+1 814-695-6794",
    "website": null,
    "address": "2814 PA-764, Duncansville, PA 16635",
    "street": "2814 PA-764",
    "city": "Duncansville",
    "state": "Pennsylvania",
    "zip": "16635",
    "rating": 3.7,
    "reviews": 3,
    "hours": "{\"Monday\": [\"11AM-12PM\"], \"Tuesday\": [\"11AM-12PM\"], \"Wednesday\": [\"11AM-12PM\"], \"Thursday\": [\"11AM-12PM\"], \"Friday\": [\"11AM-12PM\"], \"Saturday\": [\"11AM-12PM\"], \"Sunday\": [\"Closed\"]}",
    "latitude": 40.4526467,
    "longitude": -78.4306314,
    "placeId": "ChIJjfq2nimRy4kRrWcls3jrRsI",
    "googleMapsUrl": null
  },
  {
    "slug": "cash-out-gold-buyers-treasure-trove-coins-jewelry",
    "citySlug": "ebensburg",
    "name": "Cash Out Gold Buyers / Treasure Trove Coins & Jewelry",
    "phone": "+1 814-419-8419",
    "website": "http://treasuretrovecoinsandjewelry.com/",
    "address": "1661 Wilmore Rd, Ebensburg, PA 15931",
    "street": "1661 Wilmore Rd",
    "city": "Ebensburg",
    "state": "Pennsylvania",
    "zip": "15931",
    "rating": 3.5,
    "reviews": 4,
    "hours": null,
    "latitude": 40.4769508,
    "longitude": -78.7234412,
    "placeId": "ChIJSf39fx50y4kRJc1uKjWEmU0",
    "googleMapsUrl": null
  },
  {
    "slug": "gold-godz",
    "citySlug": "north-versailles",
    "name": "Gold Godz",
    "phone": "+1 412-839-1199",
    "website": "http://thegoldgodz.com/",
    "address": "1105 Lincoln Hwy, North Versailles Township, PA 15137",
    "street": "1105 Lincoln Hwy",
    "city": "North Versailles",
    "state": "Pennsylvania",
    "zip": "15137",
    "rating": 4.6,
    "reviews": 31,
    "hours": "{\"Monday\": [\"11AM-7PM\"], \"Tuesday\": [\"11AM-7PM\"], \"Wednesday\": [\"11AM-7PM\"], \"Thursday\": [\"11AM-7PM\"], \"Friday\": [\"11AM-7PM\"], \"Saturday\": [\"11AM-5PM\"], \"Sunday\": [\"11AM-3PM\"]}",
    "latitude": 40.3781324,
    "longitude": -79.8028216,
    "placeId": "ChIJRd0NQ-_pNIgRee19EHDg0io",
    "googleMapsUrl": null
  },
  {
    "slug": "pittsburgh-gold-diamonds-buyers-cash-for-gold-gift-cards",
    "citySlug": "pittsburgh",
    "name": "Pittsburgh Gold & Diamonds Buyers - Cash for Gold & Gift Cards",
    "phone": "+1 412-563-7777",
    "website": "https://www.facebook.com/pghgoldbuyers/",
    "address": "2936 W Liberty Ave, Pittsburgh, PA 15216",
    "street": "2936 W Liberty Ave",
    "city": "Pittsburgh",
    "state": "Pennsylvania",
    "zip": "15216",
    "rating": 4.5,
    "reviews": 176,
    "hours": "{\"Monday\": [\"9AM-7:30PM\"], \"Tuesday\": [\"9AM-7:30PM\"], \"Wednesday\": [\"9AM-7:30PM\"], \"Thursday\": [\"9AM-7:30PM\"], \"Friday\": [\"9AM-7:30PM\"], \"Saturday\": [\"10AM-7:30PM\"], \"Sunday\": [\"10AM-7PM\"]}",
    "latitude": 40.3944196,
    "longitude": -80.03541659999999,
    "placeId": "ChIJ0Wt0IBf3NIgRDIgOtrl485E",
    "googleMapsUrl": null
  },
  {
    "slug": "marathon-pawn",
    "citySlug": "mckees-rocks",
    "name": "Marathon Pawn",
    "phone": "+1 412-875-5459",
    "website": null,
    "address": "724 Broadway Ave, McKees Rocks, PA 15136",
    "street": "724 Broadway Ave",
    "city": "McKees Rocks",
    "state": "Pennsylvania",
    "zip": "15136",
    "rating": 3.4,
    "reviews": 25,
    "hours": "{\"Monday\": [\"9AM-7PM\"], \"Tuesday\": [\"9AM-7PM\"], \"Wednesday\": [\"9AM-7PM\"], \"Thursday\": [\"9AM-7PM\"], \"Friday\": [\"9AM-7PM\"], \"Saturday\": [\"9AM-7PM\"], \"Sunday\": [\"10AM-5PM\"]}",
    "latitude": 40.47284579999999,
    "longitude": -80.0741298,
    "placeId": "ChIJWQ_UsL_1NIgRe1cViAueEmg",
    "googleMapsUrl": null
  },
  {
    "slug": "greater-pittsburgh-quick-cash",
    "citySlug": "duquesne",
    "name": "Greater Pittsburgh Quick Cash",
    "phone": "+1 412-466-7296",
    "website": "http://www.greaterpittsburghquickcash.com/",
    "address": "1000 Duquesne Blvd, Duquesne, PA 15110",
    "street": "1000 Duquesne Blvd",
    "city": "Duquesne",
    "state": "Pennsylvania",
    "zip": "15110",
    "rating": 4.5,
    "reviews": 126,
    "hours": "{\"Monday\": [\"10AM-6PM\"], \"Tuesday\": [\"10AM-6PM\"], \"Wednesday\": [\"10AM-6PM\"], \"Thursday\": [\"10AM-6PM\"], \"Friday\": [\"10AM-6PM\"], \"Saturday\": [\"10AM-6PM\"], \"Sunday\": [\"Closed\"]}",
    "latitude": 40.3838942,
    "longitude": -79.85892369999999,
    "placeId": "ChIJCdQENRrvNIgRs2ZIozC_H9I",
    "googleMapsUrl": null
  },
  {
    "slug": "goods-unlimited-buyselltrade",
    "citySlug": "west-mifflin",
    "name": "Goods Unlimited: Buy/Sell/Trade",
    "phone": "+1 412-872-4798",
    "website": "http://goodsunlimitedbuyselltrade.com/",
    "address": "1826 Homeville Rd, West Mifflin, PA 15122",
    "street": "1826 Homeville Rd",
    "city": "West Mifflin",
    "state": "Pennsylvania",
    "zip": "15122",
    "rating": 4.2,
    "reviews": 76,
    "hours": "{\"Monday\": [\"10AM-6PM\"], \"Tuesday\": [\"10AM-6PM\"], \"Wednesday\": [\"10AM-6PM\"], \"Thursday\": [\"10AM-6PM\"], \"Friday\": [\"10AM-6PM\"], \"Saturday\": [\"10AM-6PM\"], \"Sunday\": [\"Closed\"]}",
    "latitude": 40.3650178,
    "longitude": -79.8722566,
    "placeId": "ChIJsWrdjW_vNIgR13MzqUZrvMQ",
    "googleMapsUrl": null
  },
  {
    "slug": "national-gold-exchange",
    "citySlug": "north-versailles",
    "name": "National Gold Exchange",
    "phone": "+1 412-229-8202",
    "website": "http://www.natgoldex.com/",
    "address": "355 Lincoln Hwy, North Versailles Township, PA 15137",
    "street": "355 Lincoln Hwy",
    "city": "North Versailles",
    "state": "Pennsylvania",
    "zip": "15137",
    "rating": 4.6,
    "reviews": 20,
    "hours": "{\"Monday\": [\"10AM-7:30PM\"], \"Tuesday\": [\"Closed\"], \"Wednesday\": [\"10AM-7:30PM\"], \"Thursday\": [\"10AM-7:30PM\"], \"Friday\": [\"10AM-7:30PM\"], \"Saturday\": [\"11AM-6PM\"], \"Sunday\": [\"11AM-4PM\"]}",
    "latitude": 40.3844498,
    "longitude": -79.8217576,
    "placeId": "ChIJXQq5uMTpNIgRRca1b4_QvbM",
    "googleMapsUrl": null
  },
  {
    "slug": "gelman-loan-corporation",
    "citySlug": "pittsburgh",
    "name": "Gelman Loan Corporation",
    "phone": "+1 412-661-3818",
    "website": "https://www.gelmanloan.com/",
    "address": "6490 Frankstown Ave, Pittsburgh, PA 15206",
    "street": "6490 Frankstown Ave",
    "city": "Pittsburgh",
    "state": "Pennsylvania",
    "zip": "15206",
    "rating": 4.2,
    "reviews": 31,
    "hours": "{\"Monday\": [\"10AM-3:30PM\"], \"Tuesday\": [\"10AM-3:30PM\"], \"Wednesday\": [\"Closed\"], \"Thursday\": [\"10AM-3:30PM\"], \"Friday\": [\"10AM-3:30PM\"], \"Saturday\": [\"10AM-2:30PM\"], \"Sunday\": [\"Closed\"]}",
    "latitude": 40.4603613,
    "longitude": -79.9141576,
    "placeId": "ChIJF_SdjovtNIgRn7NLLypKz4I",
    "googleMapsUrl": null
  },
  {
    "slug": "muyas-pawn-shop",
    "citySlug": "pittsburgh",
    "name": "Muyas Pawn Shop",
    "phone": "+1 412-251-5326",
    "website": "https://muyapawnshop.wordpress.com/",
    "address": "1300 Federal St, Pittsburgh, PA 15212",
    "street": "1300 Federal St",
    "city": "Pittsburgh",
    "state": "Pennsylvania",
    "zip": "15212",
    "rating": 3.3,
    "reviews": 61,
    "hours": "{\"Monday\": [\"11AM-7PM\"], \"Tuesday\": [\"11AM-7PM\"], \"Wednesday\": [\"11AM-7PM\"], \"Thursday\": [\"11AM-7PM\"], \"Friday\": [\"11AM-7PM\"], \"Saturday\": [\"11AM-7PM\"], \"Sunday\": [\"Closed\"]}",
    "latitude": 40.4567278,
    "longitude": -80.0068539,
    "placeId": "ChIJ97yiuvfzNIgRFyNULPLSmEo",
    "googleMapsUrl": null
  },
  {
    "slug": "gold-rush-pittsburgh",
    "citySlug": "pittsburgh",
    "name": "Gold Rush Pittsburgh",
    "phone": "+1 724-712-0914",
    "website": "http://goldrushco.com/",
    "address": "2830 W Liberty Ave #2, Pittsburgh, PA 15216",
    "street": "2830 W Liberty Ave #2",
    "city": "Pittsburgh",
    "state": "Pennsylvania",
    "zip": "15216",
    "rating": 4.9,
    "reviews": 481,
    "hours": "{\"Monday\": [\"10AM-7PM\"], \"Tuesday\": [\"10AM-7PM\"], \"Wednesday\": [\"10AM-7PM\"], \"Thursday\": [\"10AM-7PM\"], \"Friday\": [\"10AM-7PM\"], \"Saturday\": [\"10AM-7PM\"], \"Sunday\": [\"11AM-6PM\"]}",
    "latitude": 40.3963922,
    "longitude": -80.0323453,
    "placeId": "ChIJkZXD9Bf3NIgRfl2ZXDEkN3k",
    "googleMapsUrl": null
  },
  {
    "slug": "broffs-diamond-loan-co",
    "citySlug": "pittsburgh",
    "name": "Broff's Diamond & Loan Co.",
    "phone": "+1 412-566-1728",
    "website": "https://broffsdiamondloan.com/locations/pittsburgh/%3Futm_source%3Dgbp%26utm_medium%3Dorganic%26utm_campaign%3Dmy_business_page",
    "address": "715 Liberty Ave, Pittsburgh, PA 15222",
    "street": "715 Liberty Ave",
    "city": "Pittsburgh",
    "state": "Pennsylvania",
    "zip": "15222",
    "rating": 4.8,
    "reviews": 131,
    "hours": "{\"Monday\": [\"Closed\"], \"Tuesday\": [\"10AM-5PM\"], \"Wednesday\": [\"10AM-5PM\"], \"Thursday\": [\"10AM-7PM\"], \"Friday\": [\"10AM-5PM\"], \"Saturday\": [\"10AM-3PM\"], \"Sunday\": [\"Closed\"]}",
    "latitude": 40.4427175,
    "longitude": -79.99934549999999,
    "placeId": "ChIJ2c9YzFDxNIgR3rH6RzmHRak",
    "googleMapsUrl": null
  },
  {
    "slug": "main-loan-office-inc",
    "citySlug": "pittsburgh",
    "name": "Main Loan Office Inc",
    "phone": "+1 412-231-1155",
    "website": null,
    "address": "503 E Ohio St, Pittsburgh, PA 15212",
    "street": "503 E Ohio St",
    "city": "Pittsburgh",
    "state": "Pennsylvania",
    "zip": "15212",
    "rating": 3.9,
    "reviews": 25,
    "hours": "{\"Monday\": [\"9:30AM-3PM\"], \"Tuesday\": [\"9:30AM-3PM\"], \"Wednesday\": [\"Closed\"], \"Thursday\": [\"9:30AM-3PM\"], \"Friday\": [\"9:30AM-3PM\"], \"Saturday\": [\"9:30AM-12PM\"], \"Sunday\": [\"Closed\"]}",
    "latitude": 40.453352,
    "longitude": -80.000355,
    "placeId": "ChIJJTkBivrzNIgRN4Z3rRR6Pxs",
    "googleMapsUrl": null
  },
  {
    "slug": "fat-pocket-pawn",
    "citySlug": "north-versailles",
    "name": "Fat Pocket Pawn",
    "phone": "+1 412-829-2274",
    "website": "https://www.fatpocketpawn.biz/",
    "address": "365 Lincoln Hwy, North Versailles Township, PA 15137",
    "street": "365 Lincoln Hwy",
    "city": "North Versailles",
    "state": "Pennsylvania",
    "zip": "15137",
    "rating": 3.3,
    "reviews": 111,
    "hours": "{\"Monday\": [\"10AM-6PM\"], \"Tuesday\": [\"10AM-6PM\"], \"Wednesday\": [\"10AM-6PM\"], \"Thursday\": [\"10AM-6PM\"], \"Friday\": [\"10AM-6PM\"], \"Saturday\": [\"10AM-2PM\"], \"Sunday\": [\"Closed\"]}",
    "latitude": 40.3824936,
    "longitude": -79.8192797,
    "placeId": "ChIJnS5rr9DoNIgR1xtu7l7cnrc",
    "googleMapsUrl": null
  },
  {
    "slug": "the-exchange-buy-sell-trade",
    "citySlug": "pittsburgh",
    "name": "The Exchange Buy Sell Trade",
    "phone": "+1 412-635-3170",
    "website": "http://www.theexchange.com/",
    "address": "4776 McKnight Rd, Pittsburgh, PA 15237",
    "street": "4776 McKnight Rd",
    "city": "Pittsburgh",
    "state": "Pennsylvania",
    "zip": "15237",
    "rating": 3.9,
    "reviews": 136,
    "hours": "{\"Monday\": [\"10AM-8PM\"], \"Tuesday\": [\"10AM-8PM\"], \"Wednesday\": [\"10AM-8PM\"], \"Thursday\": [\"10AM-8PM\"], \"Friday\": [\"10AM-8PM\"], \"Saturday\": [\"10AM-8PM\"], \"Sunday\": [\"11AM-7PM\"]}",
    "latitude": 40.5223154,
    "longitude": -80.004976,
    "placeId": "ChIJ90LbDKqMNIgR9zD0lKHLw8Y",
    "googleMapsUrl": null
  },
  {
    "slug": "sparklez-jewelry-loan",
    "citySlug": "pittsburgh",
    "name": "Sparklez Jewelry & Loan",
    "phone": "+1 412-835-8805",
    "website": "https://www.sparklez.com/",
    "address": "475 Mt Lebanon Blvd, Pittsburgh, PA 15234",
    "street": "475 Mt Lebanon Blvd",
    "city": "Pittsburgh",
    "state": "Pennsylvania",
    "zip": "15234",
    "rating": 4.6,
    "reviews": 101,
    "hours": "{\"Monday\": [\"10AM-6PM\"], \"Tuesday\": [\"10AM-6PM\"], \"Wednesday\": [\"10AM-6PM\"], \"Thursday\": [\"10AM-6PM\"], \"Friday\": [\"10AM-6PM\"], \"Saturday\": [\"10AM-5PM\"], \"Sunday\": [\"Closed\"]}",
    "latitude": 40.3696992,
    "longitude": -80.031305,
    "placeId": "ChIJQanC7Ur4NIgRCYPxjP7nGkk",
    "googleMapsUrl": null
  },
  {
    "slug": "the-exchange",
    "citySlug": "monroeville",
    "name": "The Exchange",
    "phone": "+1 412-373-1000",
    "website": "http://www.theexchange.com/",
    "address": "4089 William Penn Hwy, Monroeville, PA 15146",
    "street": "4089 William Penn Hwy",
    "city": "Monroeville",
    "state": "Pennsylvania",
    "zip": "15146",
    "rating": 3.6,
    "reviews": 163,
    "hours": "{\"Monday\": [\"10AM-8PM\"], \"Tuesday\": [\"10AM-8PM\"], \"Wednesday\": [\"10AM-8PM\"], \"Thursday\": [\"10AM-8PM\"], \"Friday\": [\"10AM-9PM\"], \"Saturday\": [\"10AM-9PM\"], \"Sunday\": [\"11AM-7PM\"]}",
    "latitude": 40.4398743,
    "longitude": -79.7690689,
    "placeId": "ChIJGUYw-zvqNIgR408tMcJAjkg",
    "googleMapsUrl": null
  },
  {
    "slug": "buy-sell-outlet",
    "citySlug": "washington",
    "name": "Buy & Sell Outlet",
    "phone": "+1 724-434-0421",
    "website": "https://buy-sell-outlet.com/",
    "address": "172 S Main St, Washington, PA 15301",
    "street": "172 S Main St",
    "city": "Washington",
    "state": "Pennsylvania",
    "zip": "15301",
    "rating": 4.1,
    "reviews": 35,
    "hours": "{\"Monday\": [\"Closed\"], \"Tuesday\": [\"Closed\"], \"Wednesday\": [\"9AM-4PM\"], \"Thursday\": [\"Closed\"], \"Friday\": [\"Closed\"], \"Saturday\": [\"Closed\"], \"Sunday\": [\"Closed\"]}",
    "latitude": 40.168294,
    "longitude": -80.2446224,
    "placeId": "ChIJY2Ty4qStNYgRc8DFCKFbtZA",
    "googleMapsUrl": null
  },
  {
    "slug": "cash-converters",
    "citySlug": "reading",
    "name": "Cash Converters",
    "phone": "+1 610-796-2999",
    "website": "https://ezpawn.com/stores/pa/reading/510-kenhorst-plaza",
    "address": "510 Kenhorst Plaza, Reading, PA 19607",
    "street": "510 Kenhorst Plaza",
    "city": "Reading",
    "state": "Pennsylvania",
    "zip": "19607",
    "rating": 3.7,
    "reviews": 266,
    "hours": "{\"Monday\": [\"11AM-7PM\"], \"Tuesday\": [\"11AM-7PM\"], \"Wednesday\": [\"11AM-7PM\"], \"Thursday\": [\"11AM-7PM\"], \"Friday\": [\"11AM-7PM\"], \"Saturday\": [\"11AM-7PM\"], \"Sunday\": [\"12-5PM\"]}",
    "latitude": 40.3001614,
    "longitude": -75.949297,
    "placeId": "ChIJkXNB8qpxxokRqP2tfAD0baA",
    "googleMapsUrl": null
  },
  {
    "slug": "pawn-plus",
    "citySlug": "reading",
    "name": "Pawn Plus",
    "phone": "+1 610-373-6000",
    "website": "https://pawnplus.com/",
    "address": "524 Penn St, Reading, PA 19602",
    "street": "524 Penn St",
    "city": "Reading",
    "state": "Pennsylvania",
    "zip": "19602",
    "rating": 4.6,
    "reviews": 255,
    "hours": "{\"Monday\": [\"9:30AM-5PM\"], \"Tuesday\": [\"9:30AM-5PM\"], \"Wednesday\": [\"Closed\"], \"Thursday\": [\"9:30AM-5PM\"], \"Friday\": [\"9:30AM-5PM\"], \"Saturday\": [\"9:30AM-5PM\"], \"Sunday\": [\"Closed\"]}",
    "latitude": 40.335029,
    "longitude": -75.9268793,
    "placeId": "ChIJFcu4CMtwxokRXszaPab5Ud4",
    "googleMapsUrl": null
  },
  {
    "slug": "simple-gold-exchange-cash-for-gold-silver-and-gold-coins",
    "citySlug": "wyomissing",
    "name": "Simple Gold Exchange - CASH FOR GOLD , SILVER AND GOLD COINS",
    "phone": "+1 484-769-9746",
    "website": "https://www.facebook.com/simplegoldexchange/",
    "address": "1665 State Hill Rd, Wyomissing, PA 19610",
    "street": "1665 State Hill Rd",
    "city": "Wyomissing",
    "state": "Pennsylvania",
    "zip": "19610",
    "rating": 4.7,
    "reviews": 122,
    "hours": "{\"Monday\": [\"9AM-8PM\"], \"Tuesday\": [\"10AM-8PM\"], \"Wednesday\": [\"10AM-8PM\"], \"Thursday\": [\"10AM-8PM\"], \"Friday\": [\"10AM-8PM\"], \"Saturday\": [\"10AM-8PM\"], \"Sunday\": [\"11AM-6PM\"]}",
    "latitude": 40.3408075,
    "longitude": -75.9714266,
    "placeId": "ChIJ-7VkmYtxxokRj457PM0YX6g",
    "googleMapsUrl": null
  },
  {
    "slug": "cashing-in",
    "citySlug": "reading",
    "name": "Cashing In",
    "phone": "+1 610-685-5900",
    "website": null,
    "address": "912 Penn St, Reading, PA 19602",
    "street": "912 Penn St",
    "city": "Reading",
    "state": "Pennsylvania",
    "zip": "19602",
    "rating": 4.2,
    "reviews": 50,
    "hours": "{\"Monday\": [\"10AM-6PM\"], \"Tuesday\": [\"10AM-6PM\"], \"Wednesday\": [\"10AM-6PM\"], \"Thursday\": [\"10AM-6PM\"], \"Friday\": [\"10AM-6PM\"], \"Saturday\": [\"10AM-6PM\"], \"Sunday\": [\"Closed\"]}",
    "latitude": 40.3348881,
    "longitude": -75.9195742,
    "placeId": "ChIJq2-KxLRwxokRljfMuMtsGVI",
    "googleMapsUrl": null
  },
  {
    "slug": "national-jewelry-and-pawn",
    "citySlug": "reading",
    "name": "National Jewelry and Pawn",
    "phone": "+1 610-406-5163",
    "website": "https://www.nationaljewelryandpawn.com/",
    "address": "2100 N 11th St, Reading, PA 19604",
    "street": "2100 N 11th St",
    "city": "Reading",
    "state": "Pennsylvania",
    "zip": "19604",
    "rating": 4.6,
    "reviews": 79,
    "hours": "{\"Monday\": [\"9:30AM-5PM\"], \"Tuesday\": [\"9:30AM-5PM\"], \"Wednesday\": [\"9:30AM-5PM\"], \"Thursday\": [\"9:30AM-5PM\"], \"Friday\": [\"9:30AM-5PM\"], \"Saturday\": [\"9:30AM-5PM\"], \"Sunday\": [\"Closed\"]}",
    "latitude": 40.3672962,
    "longitude": -75.9159648,
    "placeId": "ChIJWXrfyDN3xokRDpONi6TkoG4",
    "googleMapsUrl": null
  },
  {
    "slug": "pawn-plus",
    "citySlug": "reading",
    "name": "Pawn Plus",
    "phone": "+1 610-373-7600",
    "website": "https://pawnplus.com/",
    "address": "718 Lancaster Ave, Reading, PA 19607",
    "street": "718 Lancaster Ave",
    "city": "Reading",
    "state": "Pennsylvania",
    "zip": "19607",
    "rating": 4.6,
    "reviews": 131,
    "hours": "{\"Monday\": [\"9:30AM-5PM\"], \"Tuesday\": [\"Closed\"], \"Wednesday\": [\"9:30AM-5PM\"], \"Thursday\": [\"9:30AM-5PM\"], \"Friday\": [\"9:30AM-5PM\"], \"Saturday\": [\"9:30AM-5PM\"], \"Sunday\": [\"Closed\"]}",
    "latitude": 40.3168208,
    "longitude": -75.9382148,
    "placeId": "ChIJpzGVDudwxokR9dZiOJe04Io",
    "googleMapsUrl": null
  },
  {
    "slug": "we-buy-everything-philadelphia",
    "citySlug": "philadelphia",
    "name": "We Buy Everything - Philadelphia",
    "phone": "+1 215-677-0200",
    "website": "http://www.webuyeverything.com/",
    "address": "1900 Grant Ave Unit C, Philadelphia, PA 19115",
    "street": "1900 Grant Ave Unit C",
    "city": "Philadelphia",
    "state": "Pennsylvania",
    "zip": "19115",
    "rating": 4.5,
    "reviews": 452,
    "hours": "{\"Monday\": [\"10AM-6PM\"], \"Tuesday\": [\"10AM-6PM\"], \"Wednesday\": [\"10AM-6PM\"], \"Thursday\": [\"10AM-6PM\"], \"Friday\": [\"10AM-6PM\"], \"Saturday\": [\"10AM-4PM\"], \"Sunday\": [\"10AM-3PM\"]}",
    "latitude": 40.08396,
    "longitude": -75.03551399999999,
    "placeId": "ChIJF4jGHuuzxokR8P7OdhO2-yw",
    "googleMapsUrl": null
  },
  {
    "slug": "we-buy-everything-pawn-shop-city-ave",
    "citySlug": "merion-station",
    "name": "We Buy Everything Pawn Shop - City Ave",
    "phone": "+1 610-206-3450",
    "website": "https://webuyeverything.com/",
    "address": "225 City Ave, Merion Station, PA 19066",
    "street": "225 City Ave",
    "city": "Merion Station",
    "state": "Pennsylvania",
    "zip": "19066",
    "rating": 4.1,
    "reviews": 40,
    "hours": "{\"Monday\": [\"10AM-6PM\"], \"Tuesday\": [\"10AM-6PM\"], \"Wednesday\": [\"10AM-6PM\"], \"Thursday\": [\"10AM-6PM\"], \"Friday\": [\"10AM-6PM\"], \"Saturday\": [\"10AM-4PM\"], \"Sunday\": [\"10AM-3PM\"]}",
    "latitude": 39.9968443,
    "longitude": -75.2360933,
    "placeId": "ChIJR7OWB0nHxokRvEGeD6OK40g",
    "googleMapsUrl": null
  },
  {
    "slug": "ibest-shop",
    "citySlug": "springfield",
    "name": "iBest Shop",
    "phone": "+1 484-245-6666",
    "website": "https://www.facebook.com/IBest-Shop-inc-108138917701144/",
    "address": "418 Baltimore Pike, Springfield, PA 19064",
    "street": "418 Baltimore Pike",
    "city": "Springfield",
    "state": "Pennsylvania",
    "zip": "19064",
    "rating": 4.7,
    "reviews": 259,
    "hours": "{\"Monday\": [\"9AM-10PM\"], \"Tuesday\": [\"9AM-10PM\"], \"Wednesday\": [\"9AM-10PM\"], \"Thursday\": [\"9AM-10PM\"], \"Friday\": [\"9AM-10PM\"], \"Saturday\": [\"9AM-10PM\"], \"Sunday\": [\"9AM-10PM\"]}",
    "latitude": 39.9213521,
    "longitude": -75.3222,
    "placeId": "ChIJJfrxYyrDxokRaIbysy4E2D8",
    "googleMapsUrl": null
  },
  {
    "slug": "fair-4-all-trading-post",
    "citySlug": "philadelphia",
    "name": "Fair 4 All Trading Post",
    "phone": "+1 215-821-3021",
    "website": null,
    "address": "14260 Bustleton Ave, Philadelphia, PA 19116",
    "street": "14260 Bustleton Ave",
    "city": "Philadelphia",
    "state": "Pennsylvania",
    "zip": "19116",
    "rating": 4.8,
    "reviews": 117,
    "hours": "{\"Monday\": [\"Closed\"], \"Tuesday\": [\"10AM-6PM\"], \"Wednesday\": [\"10AM-6PM\"], \"Thursday\": [\"10AM-6PM\"], \"Friday\": [\"10AM-6PM\"], \"Saturday\": [\"10AM-4PM\"], \"Sunday\": [\"Closed\"]}",
    "latitude": 40.1327864,
    "longitude": -75.0118482,
    "placeId": "ChIJdxdq1fuzxokRAD56AzHGQHY",
    "googleMapsUrl": null
  },
  {
    "slug": "mega-pawn",
    "citySlug": "morrisville",
    "name": "Mega Pawn",
    "phone": "+1 215-932-0607",
    "website": "https://megapawn.net/",
    "address": "334 W Bridge St, Morrisville, PA 19067",
    "street": "334 W Bridge St",
    "city": "Morrisville",
    "state": "Pennsylvania",
    "zip": "19067",
    "rating": 4.9,
    "reviews": 429,
    "hours": "{\"Monday\": [\"10AM-6PM\"], \"Tuesday\": [\"10AM-6PM\"], \"Wednesday\": [\"10AM-6PM\"], \"Thursday\": [\"10AM-6PM\"], \"Friday\": [\"10AM-6PM\"], \"Saturday\": [\"10AM-6PM\"], \"Sunday\": [\"Closed\"]}",
    "latitude": 40.2055273,
    "longitude": -74.780981,
    "placeId": "ChIJI1-pZ9tXwYkRfMvDHPm2roA",
    "googleMapsUrl": null
  },
  {
    "slug": "woodland-money-loan",
    "citySlug": "philadelphia",
    "name": "Woodland Money Loan",
    "phone": "+1 215-744-8920",
    "website": null,
    "address": "4701 Frankford Ave, Philadelphia, PA 19124",
    "street": "4701 Frankford Ave",
    "city": "Philadelphia",
    "state": "Pennsylvania",
    "zip": "19124",
    "rating": 4.9,
    "reviews": 834,
    "hours": "{\"Monday\": [\"9AM-5PM\"], \"Tuesday\": [\"9AM-5PM\"], \"Wednesday\": [\"9AM-5PM\"], \"Thursday\": [\"9AM-5PM\"], \"Friday\": [\"9AM-5PM\"], \"Saturday\": [\"9AM-3PM\"], \"Sunday\": [\"Closed\"]}",
    "latitude": 40.0167631,
    "longitude": -75.0834035,
    "placeId": "ChIJMxdTeJy3xokRjpWgw0isjkM",
    "googleMapsUrl": null
  },
  {
    "slug": "cash-express-pawn-shop",
    "citySlug": "philadelphia",
    "name": "Cash Express Pawn Shop",
    "phone": "+1 215-922-1560",
    "website": "http://www.pawnphiladelphia.com/",
    "address": "731 Chestnut St, Philadelphia, PA 19106",
    "street": "731 Chestnut St",
    "city": "Philadelphia",
    "state": "Pennsylvania",
    "zip": "19106",
    "rating": 3.3,
    "reviews": 53,
    "hours": "{\"Monday\": [\"10AM-5:30PM\"], \"Tuesday\": [\"10AM-5:30PM\"], \"Wednesday\": [\"10AM-5:30PM\"], \"Thursday\": [\"10AM-5:30PM\"], \"Friday\": [\"10AM-5:30PM\"], \"Saturday\": [\"10:30AM-3:30PM\"], \"Sunday\": [\"Closed\"]}",
    "latitude": 39.9496626,
    "longitude": -75.15352969999999,
    "placeId": "ChIJ2e8FkYLIxokRGhcqVE1GaIo",
    "googleMapsUrl": null
  },
  {
    "slug": "8th-street-gold-diamond-buyers-llc",
    "citySlug": "philadelphia",
    "name": "8th Street Gold & Diamond Buyers LLC",
    "phone": "+1 215-238-6570",
    "website": "http://8thstreetbuyers1.com/",
    "address": "109 S 8th St, Philadelphia, PA 19106",
    "street": "109 S 8th St",
    "city": "Philadelphia",
    "state": "Pennsylvania",
    "zip": "19106",
    "rating": 4.9,
    "reviews": 215,
    "hours": "{\"Monday\": [\"10AM-5PM\"], \"Tuesday\": [\"10AM-5PM\"], \"Wednesday\": [\"10AM-5PM\"], \"Thursday\": [\"10AM-5PM\"], \"Friday\": [\"10AM-5PM\"], \"Saturday\": [\"10AM-5PM\"], \"Sunday\": [\"Closed\"]}",
    "latitude": 39.9492238,
    "longitude": -75.153819,
    "placeId": "ChIJUXRumILIxokRhtQ0PvPej30",
    "googleMapsUrl": null
  },
  {
    "slug": "cash-for-gold-delaware-county-jewelry-open-7-days-a-week-cash-for-gold-silver-watches-diamonds",
    "citySlug": "folsom",
    "name": "CASH FOR GOLD Delaware County Jewelry - Open 7 Days A Week - CASH FOR GOLD, SILVER, WATCHES, DIAMONDS",
    "phone": "+1 484-540-7916",
    "website": null,
    "address": "443 MacDade Boulevard, Folsom, PA 19033",
    "street": "443 MacDade Boulevard",
    "city": "Folsom",
    "state": "Pennsylvania",
    "zip": "19033",
    "rating": 4.9,
    "reviews": 338,
    "hours": "{\"Monday\": [\"10AM-7PM\"], \"Tuesday\": [\"10AM-7PM\"], \"Wednesday\": [\"10AM-7PM\"], \"Thursday\": [\"10AM-7PM\"], \"Friday\": [\"10AM-7PM\"], \"Saturday\": [\"10:30AM-7PM\"], \"Sunday\": [\"10AM-4PM\"]}",
    "latitude": 39.8899413,
    "longitude": -75.32586169999999,
    "placeId": "ChIJwZpqJ47CxokRDRpKRSpZ6SU",
    "googleMapsUrl": null
  },
  {
    "slug": "q-pawn",
    "citySlug": "philadelphia",
    "name": "Q-pawn",
    "phone": null,
    "website": "https://www.ebay.com/usr/q-pawn",
    "address": "10077 Sandmeyer Ln #4, Philadelphia, PA 19116",
    "street": "10077 Sandmeyer Ln #4",
    "city": "Philadelphia",
    "state": "Pennsylvania",
    "zip": "19116",
    "rating": 5,
    "reviews": 1,
    "hours": null,
    "latitude": 40.1154841,
    "longitude": -75.03675609999999,
    "placeId": "ChIJF-0LsXizxokRJ2aodHmHAgY",
    "googleMapsUrl": null
  },
  {
    "slug": "front-street-sales-outlet",
    "citySlug": "philadelphia",
    "name": "Front Street Sales Outlet",
    "phone": "+1 215-423-9665",
    "website": "https://www.frontstreetpawn.com/",
    "address": "2746 N Front St, Philadelphia, PA 19133",
    "street": "2746 N Front St",
    "city": "Philadelphia",
    "state": "Pennsylvania",
    "zip": "19133",
    "rating": 4.3,
    "reviews": 19,
    "hours": "{\"Monday\": [\"10AM-4PM\"], \"Tuesday\": [\"10AM-4PM\"], \"Wednesday\": [\"10AM-4PM\"], \"Thursday\": [\"10AM-4PM\"], \"Friday\": [\"10AM-4PM\"], \"Saturday\": [\"Closed\"], \"Sunday\": [\"Closed\"]}",
    "latitude": 39.9922448,
    "longitude": -75.1307372,
    "placeId": "ChIJ2U7K1iHIxokRnGvQ3BwTyTs",
    "googleMapsUrl": null
  },
  {
    "slug": "kensington-gold-silver-exchange",
    "citySlug": "philadelphia",
    "name": "Kensington Gold & Silver Exchange",
    "phone": "+1 215-425-4955",
    "website": "https://www.phillypawnbroker.com/",
    "address": "1802 E Allegheny Ave, Philadelphia, PA 19134",
    "street": "1802 E Allegheny Ave",
    "city": "Philadelphia",
    "state": "Pennsylvania",
    "zip": "19134",
    "rating": 4.6,
    "reviews": 79,
    "hours": "{\"Monday\": [\"9:30AM-4:45PM\"], \"Tuesday\": [\"9:30AM-4:45PM\"], \"Wednesday\": [\"9:30AM-4:45PM\"], \"Thursday\": [\"9:30AM-4:45PM\"], \"Friday\": [\"9:30AM-4:45PM\"], \"Saturday\": [\"9:30AM-1:45PM\"], \"Sunday\": [\"Closed\"]}",
    "latitude": 39.99608629999999,
    "longitude": -75.1134115,
    "placeId": "ChIJeWA5JtS3xokRljhNLhr6QY8",
    "googleMapsUrl": null
  },
  {
    "slug": "lous-jewelry-pawn",
    "citySlug": "upper-darby",
    "name": "Lou's Jewelry & Pawn",
    "phone": "+1 833-449-2119",
    "website": "https://louspawn.com/",
    "address": "29 S 69th St, Upper Darby Township, PA 19082",
    "street": "29 S 69th St",
    "city": "Upper Darby",
    "state": "Pennsylvania",
    "zip": "19082",
    "rating": 4,
    "reviews": 373,
    "hours": "{\"Monday\": [\"9:30AM-5PM\"], \"Tuesday\": [\"9:30AM-5PM\"], \"Wednesday\": [\"9:30AM-5PM\"], \"Thursday\": [\"9:30AM-5PM\"], \"Friday\": [\"9:30AM-5PM\"], \"Saturday\": [\"9:30AM-5PM\"], \"Sunday\": [\"Closed\"]}",
    "latitude": 39.9608042,
    "longitude": -75.2586796,
    "placeId": "ChIJtcWsETDBxokRf_VmHdBLhTg",
    "googleMapsUrl": null
  },
  {
    "slug": "major-liquidations-buy-sell-trade-gold-electronics",
    "citySlug": "philadelphia",
    "name": "Major Liquidations - Buy, Sell, Trade Gold & Electronics",
    "phone": "+1 267-764-1514",
    "website": "https://www.instagram.com/majorliquidationsllc/",
    "address": "3050-52 Kensington Ave, Philadelphia, PA 19134",
    "street": "3050-52 Kensington Ave",
    "city": "Philadelphia",
    "state": "Pennsylvania",
    "zip": "19134",
    "rating": 4.6,
    "reviews": null,
    "hours": "{\"Sunday\": [\"Closed\"]}",
    "latitude": 39.9948518,
    "longitude": -75.11682929999999,
    "placeId": "ChIJXy3NiO-3xokRMeAJ1fPOZm0",
    "googleMapsUrl": null
  },
  {
    "slug": "united-check-cashing",
    "citySlug": "philadelphia",
    "name": "United Check Cashing",
    "phone": "+1 215-468-4200",
    "website": "https://www.myunitedcheckcashing.com/",
    "address": "1123 S Broad St, Philadelphia, PA 19147",
    "street": "1123 S Broad St",
    "city": "Philadelphia",
    "state": "Pennsylvania",
    "zip": "19147",
    "rating": 4.3,
    "reviews": null,
    "hours": "{\"Sunday\": [\"9AM-5PM\"]}",
    "latitude": 39.9370762,
    "longitude": -75.166662,
    "placeId": "ChIJtxDkgRfGxokRdLv3iBSWnko",
    "googleMapsUrl": null
  },
  {
    "slug": "king-of-gold-cash-for-gold-silver-gold-coins",
    "citySlug": "norwood",
    "name": "King of Gold - Cash for Gold, Silver & Gold Coins",
    "phone": "+1 484-494-7196",
    "website": null,
    "address": "608 Chester Pike, Norwood, PA 19074",
    "street": "608 Chester Pike",
    "city": "Norwood",
    "state": "Pennsylvania",
    "zip": "19074",
    "rating": 4.9,
    "reviews": null,
    "hours": "{\"Sunday\": [\"10AM-4PM\"]}",
    "latitude": 39.8859384,
    "longitude": -75.30178269999999,
    "placeId": "ChIJ85Dj1ubDxokRn2eJlb_oO-c",
    "googleMapsUrl": null
  },
  {
    "slug": "cottman-cash-for-gold",
    "citySlug": "philadelphia",
    "name": "Cottman cash for gold",
    "phone": "+1 215-335-2300",
    "website": "https://www.cottmancashforgold.com/",
    "address": "2444 Cottman Ave, Philadelphia, PA 19149",
    "street": "2444 Cottman Ave",
    "city": "Philadelphia",
    "state": "Pennsylvania",
    "zip": "19149",
    "rating": 3.1,
    "reviews": null,
    "hours": "{\"Sunday\": [\"Closed\"]}",
    "latitude": 40.0465115,
    "longitude": -75.05838589999999,
    "placeId": "ChIJczRqmCO1xokRyF0sSR7AVEw",
    "googleMapsUrl": null
  },
  {
    "slug": "darby-pawn-shop-llc",
    "citySlug": "darby",
    "name": "Darby Pawn Shop LLC",
    "phone": "+1 610-532-1919",
    "website": null,
    "address": "17 S MacDade Blvd, Darby, PA 19023",
    "street": "17 S MacDade Blvd",
    "city": "Darby",
    "state": "Pennsylvania",
    "zip": "19023",
    "rating": 3.7,
    "reviews": null,
    "hours": "{\"Sunday\": [\"Closed\"]}",
    "latitude": 39.9175958,
    "longitude": -75.264892,
    "placeId": "ChIJA8pNR-_DxokR47wYdT57yVs",
    "googleMapsUrl": null
  },
  {
    "slug": "formans-pawnshop-expert-watch-repair",
    "citySlug": "philadelphia",
    "name": "Forman's Pawnshop & Expert Watch Repair",
    "phone": "+1 215-735-3073",
    "website": "http://formanspawn.com/",
    "address": "626 S 12th St, Philadelphia, PA 19147",
    "street": "626 S 12th St",
    "city": "Philadelphia",
    "state": "Pennsylvania",
    "zip": "19147",
    "rating": 3.5,
    "reviews": null,
    "hours": "{\"Sunday\": [\"Closed\"]}",
    "latitude": 39.942428,
    "longitude": -75.162093,
    "placeId": "ChIJdfrRviPGxokRXT9jZFI0BH4",
    "googleMapsUrl": null
  },
  {
    "slug": "cheltenham-pawn-shop-llc",
    "citySlug": "wyncote",
    "name": "Cheltenham Pawn Shop, LLC",
    "phone": "+1 215-884-0200",
    "website": "http://www.cheltenhampawnshop.com/",
    "address": "8160 Ogontz Ave, Wyncote, PA 19095",
    "street": "8160 Ogontz Ave",
    "city": "Wyncote",
    "state": "Pennsylvania",
    "zip": "19095",
    "rating": 4.1,
    "reviews": null,
    "hours": "{\"Sunday\": [\"Closed\"]}",
    "latitude": 40.0768132,
    "longitude": -75.1598159,
    "placeId": "ChIJYywpIf-5xokRhhqtG74cJuQ",
    "googleMapsUrl": null
  },
  {
    "slug": "warminster-cash-exchange-pawn-shop",
    "citySlug": "warminster",
    "name": "Warminster Cash Exchange Pawn Shop",
    "phone": "+1 215-675-2274",
    "website": "https://warminstercashexchange.com/",
    "address": "223 York Rd, Warminster, PA 18974",
    "street": "223 York Rd",
    "city": "Warminster",
    "state": "Pennsylvania",
    "zip": "18974",
    "rating": 3.8,
    "reviews": null,
    "hours": "{\"Sunday\": [\"Closed\"]}",
    "latitude": 40.1962246,
    "longitude": -75.1015735,
    "placeId": "ChIJAXrD8_uuxokRz3ffAU0pQ_A",
    "googleMapsUrl": null
  },
  {
    "slug": "williams-jewelry-cash-for-gold",
    "citySlug": "philadelphia",
    "name": "Williams Jewelry Cash For Gold",
    "phone": "+1 484-687-3203",
    "website": "http://williamjewelry.com/",
    "address": "1630 W Passyunk Ave, Philadelphia, PA 19145",
    "street": "1630 W Passyunk Ave",
    "city": "Philadelphia",
    "state": "Pennsylvania",
    "zip": "19145",
    "rating": 4.7,
    "reviews": null,
    "hours": "{\"Sunday\": [\"10AM-7:30PM\"]}",
    "latitude": 39.9245037,
    "longitude": -75.1738022,
    "placeId": "ChIJF2EE2pTHxokRBS2cwVjq1-g",
    "googleMapsUrl": null
  },
  {
    "slug": "gold-rush-cash-for-gold-pawn-shop",
    "citySlug": "huntingdon-valley",
    "name": "Gold Rush CASH FOR GOLD PAWN SHOP",
    "phone": "+1 215-938-1400",
    "website": null,
    "address": "620 Welsh Rd, Huntingdon Valley, PA 19006",
    "street": "620 Welsh Rd",
    "city": "Huntingdon Valley",
    "state": "Pennsylvania",
    "zip": "19006",
    "rating": 4.6,
    "reviews": null,
    "hours": "{\"Sunday\": [\"10:30AM-5PM\"]}",
    "latitude": 40.1193675,
    "longitude": -75.0680777,
    "placeId": "ChIJexmBKI-xxokRcpDBeJTCtWE",
    "googleMapsUrl": null
  },
  {
    "slug": "one-stop-pawn-shop",
    "citySlug": "norristown",
    "name": "One Stop Pawn Shop",
    "phone": "+1 610-272-7680",
    "website": "https://onestoppawn-norristownpa.bestlocal.business/",
    "address": "34 W Main St, Norristown, PA 19401",
    "street": "34 W Main St",
    "city": "Norristown",
    "state": "Pennsylvania",
    "zip": "19401",
    "rating": 2.7,
    "reviews": null,
    "hours": "{\"Sunday\": [\"Closed\"]}",
    "latitude": 40.114783,
    "longitude": -75.3456071,
    "placeId": "ChIJw9k06xyWxokRnBkBuT2NaRA",
    "googleMapsUrl": null
  },
  {
    "slug": "abrahamharold-ta-simpsons",
    "citySlug": "philadelphia",
    "name": "AbrahamHarold t/a Simpsons",
    "phone": "+1 215-925-2712",
    "website": null,
    "address": "116 S 12th St, Philadelphia, PA 19107",
    "street": "116 S 12th St",
    "city": "Philadelphia",
    "state": "Pennsylvania",
    "zip": "19107",
    "rating": 3.3,
    "reviews": null,
    "hours": "{\"Sunday\": [\"Closed\"]}",
    "latitude": 39.9497995,
    "longitude": -75.16052719999999,
    "placeId": "ChIJGY-hsijGxokRSw7y8qi_d2w",
    "googleMapsUrl": null
  },
  {
    "slug": "carver-w-reed-co",
    "citySlug": "philadelphia",
    "name": "Carver W Reed & Co.",
    "phone": "+1 215-923-1443",
    "website": "http://www.carverwreed.com/",
    "address": "121 S 10th St, Philadelphia, PA 19107",
    "street": "121 S 10th St",
    "city": "Philadelphia",
    "state": "Pennsylvania",
    "zip": "19107",
    "rating": 4.6,
    "reviews": 20,
    "hours": "{\"Monday\": [\"10AM-3PM\"], \"Tuesday\": [\"10AM-3PM\"], \"Wednesday\": [\"10AM-3PM\"], \"Thursday\": [\"10AM-3PM\"], \"Friday\": [\"10AM-3PM\"], \"Saturday\": [\"Closed\"], \"Sunday\": [\"Closed\"]}",
    "latitude": 39.9491409,
    "longitude": -75.1570217,
    "placeId": "ChIJfz0NZCjGxokR-TEg91A5ZWM",
    "googleMapsUrl": null
  },
  {
    "slug": "touch-of-gold-jewelers",
    "citySlug": "philadelphia",
    "name": "Touch of Gold Jewelers",
    "phone": "+1 215-922-1595",
    "website": "http://www.touchofgoldjewelers.com/",
    "address": "640 South St, Philadelphia, PA 19147",
    "street": "640 South St",
    "city": "Philadelphia",
    "state": "Pennsylvania",
    "zip": "19147",
    "rating": 4.9,
    "reviews": 159,
    "hours": "{\"Monday\": [\"11AM-8PM\"], \"Tuesday\": [\"11AM-8PM\"], \"Wednesday\": [\"11AM-8PM\"], \"Thursday\": [\"11AM-8PM\"], \"Friday\": [\"11AM-8PM\"], \"Saturday\": [\"11AM-8PM\"], \"Sunday\": [\"11AM-7PM\"]}",
    "latitude": 39.9419337,
    "longitude": -75.1535576,
    "placeId": "ChIJQWxezgfJxokRRlh_40iwtho",
    "googleMapsUrl": null
  },
  {
    "slug": "society-hill-loan",
    "citySlug": "philadelphia",
    "name": "Society Hill Loan",
    "phone": null,
    "website": null,
    "address": "Philadelphia, PA 19147",
    "street": null,
    "city": "Philadelphia",
    "state": "Pennsylvania",
    "zip": "19147",
    "rating": 5,
    "reviews": 2,
    "hours": null,
    "latitude": 39.942272,
    "longitude": -75.1537905,
    "placeId": "ChIJhZP-D57IxokRY0EJ_MqUuNY",
    "googleMapsUrl": null
  },
  {
    "slug": "paymore-buy-sell-trade-electronics",
    "citySlug": "philadelphia",
    "name": "PayMore - Buy, Sell & Trade Electronics",
    "phone": "+1 267-731-6850",
    "website": "http://bustletonpa.paymore.com/%3Futm_source%3Dgoogle%26utm_medium%3Dorganic%26utm_campaign%3DGBP%26utm_content%3Dwebsite_button",
    "address": "10090 Roosevelt Blvd, Philadelphia, PA 19116",
    "street": "10090 Roosevelt Blvd",
    "city": "Philadelphia",
    "state": "Pennsylvania",
    "zip": "19116",
    "rating": 4.6,
    "reviews": 275,
    "hours": "{\"Monday\": [\"10AM-6PM\"], \"Tuesday\": [\"10AM-6PM\"], \"Wednesday\": [\"10AM-6PM\"], \"Thursday\": [\"10AM-6PM\"], \"Friday\": [\"10AM-6PM\"], \"Saturday\": [\"11AM-5PM\"], \"Sunday\": [\"Closed\"]}",
    "latitude": 40.0960962,
    "longitude": -75.01487689999999,
    "placeId": "ChIJxZ504pmzxokR2QCMzpjrWQM",
    "googleMapsUrl": null
  },
  {
    "slug": "a-plus-precious-metals",
    "citySlug": "philadelphia",
    "name": "A Plus Precious Metals",
    "phone": "+1 215-821-3751",
    "website": null,
    "address": "6907 Torresdale Ave, Philadelphia, PA 19135",
    "street": "6907 Torresdale Ave",
    "city": "Philadelphia",
    "state": "Pennsylvania",
    "zip": "19135",
    "rating": 3.9,
    "reviews": 30,
    "hours": "{\"Monday\": [\"10AM-4PM\"], \"Tuesday\": [\"10AM-4PM\"], \"Wednesday\": [\"10AM-4PM\"], \"Thursday\": [\"10AM-4PM\"], \"Friday\": [\"10AM-4PM\"], \"Saturday\": [\"Closed\"], \"Sunday\": [\"Closed\"]}",
    "latitude": 40.025944,
    "longitude": -75.042717,
    "placeId": "ChIJPczSiDS0xokRjvg76xzoonY",
    "googleMapsUrl": null
  },
  {
    "slug": "carlos-jewelry-exchange",
    "citySlug": "dickson-city",
    "name": "Carlo's Jewelry Exchange",
    "phone": "+1 570-489-1100",
    "website": "https://www.cjediamonds.com/",
    "address": "1500 Main St, Dickson City, PA 18447",
    "street": "1500 Main St",
    "city": "Dickson City",
    "state": "Pennsylvania",
    "zip": "18447",
    "rating": 4.9,
    "reviews": 161,
    "hours": "{\"Monday\": [\"10AM-5:30PM\"], \"Tuesday\": [\"10AM-5:30PM\"], \"Wednesday\": [\"10AM-5:30PM\"], \"Thursday\": [\"10AM-5:30PM\"], \"Friday\": [\"10AM-5:30PM\"], \"Saturday\": [\"10AM-4PM\"], \"Sunday\": [\"11:30AM-4PM\"]}",
    "latitude": 41.4686019,
    "longitude": -75.61119479999999,
    "placeId": "ChIJb3VhsQ3axIkRkW6zxK7T-gY",
    "googleMapsUrl": null
  },
  {
    "slug": "a1-scranton-gold-silver-buyers",
    "citySlug": "scranton",
    "name": "A1 Scranton Gold & Silver Buyers",
    "phone": "+1 570-335-0795",
    "website": "https://scrantongoldbuyers.com/",
    "address": "107 W Market St, Scranton, PA 18508",
    "street": "107 W Market St",
    "city": "Scranton",
    "state": "Pennsylvania",
    "zip": "18508",
    "rating": 4.8,
    "reviews": 147,
    "hours": "{\"Monday\": [\"10AM-6PM\"], \"Tuesday\": [\"10AM-6PM\"], \"Wednesday\": [\"10AM-6PM\"], \"Thursday\": [\"10AM-6PM\"], \"Friday\": [\"10AM-6PM\"], \"Saturday\": [\"Closed\"], \"Sunday\": [\"Closed\"]}",
    "latitude": 41.4379451,
    "longitude": -75.6574249,
    "placeId": "ChIJt15n9RnZxIkR8vlIqMEiGkg",
    "googleMapsUrl": null
  },
  {
    "slug": "cashcash4gold",
    "citySlug": "scranton",
    "name": "Cashcash4gold",
    "phone": "+1 570-497-7735",
    "website": "http://www.cashcash4gold.com/",
    "address": "Located In Pacific Auto Office, 1826 N Main Ave, Scranton, PA 18508",
    "street": "Located In Pacific Auto Office, 1826 N Main Ave",
    "city": "Scranton",
    "state": "Pennsylvania",
    "zip": "18508",
    "rating": 4.3,
    "reviews": 34,
    "hours": "{\"Monday\": [\"10AM-5PM\"], \"Tuesday\": [\"10AM-5PM\"], \"Wednesday\": [\"10AM-5PM\"], \"Thursday\": [\"10AM-5PM\"], \"Friday\": [\"10AM-5PM\"], \"Saturday\": [\"1-2PM\"], \"Sunday\": [\"1-2PM\"]}",
    "latitude": 41.4370145,
    "longitude": -75.6578167,
    "placeId": "ChIJa95slxnZxIkRRmX0ms_YplE",
    "googleMapsUrl": null
  },
  {
    "slug": "gold-2-cash-the-electric-city-trading-post-buy-sell-trade-pawn-shop-jewelry-company",
    "citySlug": "scranton",
    "name": "Gold 2 Cash - The Electric City Trading Post - Buy Sell Trade Pawn Shop - Jewelry Company",
    "phone": "+1 570-881-0386",
    "website": "http://www.facebook.com/jeffstradingpost2",
    "address": "301 Adams Ave, Scranton, PA 18503",
    "street": "301 Adams Ave",
    "city": "Scranton",
    "state": "Pennsylvania",
    "zip": "18503",
    "rating": 4.1,
    "reviews": 57,
    "hours": null,
    "latitude": 41.40848219999999,
    "longitude": -75.66102409999999,
    "placeId": "ChIJY-dPTtHexIkRMDAWhvbsJ3c",
    "googleMapsUrl": null
  },
  {
    "slug": "jeffs-trading-post",
    "citySlug": "scranton",
    "name": "Jeffs Trading Post",
    "phone": "+1 570-881-0386",
    "website": "https://m.facebook.com/jeffstradingpost/",
    "address": "238 N Main Ave, Scranton, PA 18504",
    "street": "238 N Main Ave",
    "city": "Scranton",
    "state": "Pennsylvania",
    "zip": "18504",
    "rating": 2.4,
    "reviews": 42,
    "hours": null,
    "latitude": 41.4142069,
    "longitude": -75.6780122,
    "placeId": "ChIJk77OcS3fxIkRu_3q-1B2qiw",
    "googleMapsUrl": null
  },
  {
    "slug": "pawn-plus",
    "citySlug": "lancaster",
    "name": "Pawn Plus",
    "phone": "+1 717-290-6000",
    "website": "https://pawnplus.com/",
    "address": "46 W King St, Lancaster, PA 17603",
    "street": "46 W King St",
    "city": "Lancaster",
    "state": "Pennsylvania",
    "zip": "17603",
    "rating": 3.6,
    "reviews": 197,
    "hours": "{\"Monday\": [\"9:30AM-5PM\"], \"Tuesday\": [\"9:30AM-5PM\"], \"Wednesday\": [\"Closed\"], \"Thursday\": [\"9:30AM-5PM\"], \"Friday\": [\"9:30AM-5PM\"], \"Saturday\": [\"9:30AM-5PM\"], \"Sunday\": [\"Closed\"]}",
    "latitude": 40.0376281,
    "longitude": -76.3073367,
    "placeId": "ChIJSSQ9PfIkxokRQj01kHTit9Q",
    "googleMapsUrl": null
  },
  {
    "slug": "pawn-plus",
    "citySlug": "allentown",
    "name": "Pawn Plus",
    "phone": "+1 833-272-9648",
    "website": "https://pawnplus.com/",
    "address": "636 N 7th St, Allentown, PA 18102",
    "street": "636 N 7th St",
    "city": "Allentown",
    "state": "Pennsylvania",
    "zip": "18102",
    "rating": 4.4,
    "reviews": 149,
    "hours": "{\"Monday\": [\"9:30AM-5PM\"], \"Tuesday\": [\"9:30AM-5PM\"], \"Wednesday\": [\"Closed\"], \"Thursday\": [\"9:30AM-5PM\"], \"Friday\": [\"9:30AM-5PM\"], \"Saturday\": [\"9:30AM-5PM\"], \"Sunday\": [\"Closed\"]}",
    "latitude": 40.6114254,
    "longitude": -75.4764199,
    "placeId": "ChIJ18wgJXc5xIkRNPCPKFmjyvc",
    "googleMapsUrl": null
  },
  {
    "slug": "airport-pawn",
    "citySlug": "allentown",
    "name": "Airport Pawn",
    "phone": "+1 610-351-5051",
    "website": "https://www.airportpawn.com/",
    "address": "1195 Airport Rd, Allentown, PA 18109",
    "street": "1195 Airport Rd",
    "city": "Allentown",
    "state": "Pennsylvania",
    "zip": "18109",
    "rating": 4.3,
    "reviews": 120,
    "hours": "{\"Monday\": [\"10AM-6PM\"], \"Tuesday\": [\"10AM-6PM\"], \"Wednesday\": [\"10AM-6PM\"], \"Thursday\": [\"10AM-6PM\"], \"Friday\": [\"10AM-6PM\"], \"Saturday\": [\"Closed\"], \"Sunday\": [\"Closed\"]}",
    "latitude": 40.6286766,
    "longitude": -75.4394788,
    "placeId": "ChIJlREMGSw5xIkRJjLn-EZBdIg",
    "googleMapsUrl": null
  },
  {
    "slug": "pawn-america-inc",
    "citySlug": "allentown",
    "name": "Pawn America Inc.",
    "phone": "+1 610-776-1767",
    "website": "https://www.pawnamericainc.net/",
    "address": "923 Hamilton St, Allentown, PA 18101",
    "street": "923 Hamilton St",
    "city": "Allentown",
    "state": "Pennsylvania",
    "zip": "18101",
    "rating": 4.1,
    "reviews": 62,
    "hours": "{\"Monday\": [\"10AM-5:30PM\"], \"Tuesday\": [\"10AM-5:30PM\"], \"Wednesday\": [\"10AM-5:30PM\"], \"Thursday\": [\"10AM-5:30PM\"], \"Friday\": [\"10AM-5:30PM\"], \"Saturday\": [\"10AM-3PM\"], \"Sunday\": [\"Closed\"]}",
    "latitude": 40.6010824,
    "longitude": -75.4764718,
    "placeId": "ChIJOaPWan45xIkR0kz9_u2903U",
    "googleMapsUrl": null
  },
  {
    "slug": "ez-money-ii-buy-sell-trade",
    "citySlug": "bethlehem",
    "name": "EZ Money II Buy Sell Trade",
    "phone": "+1 610-882-2425",
    "website": "http://www.ezmoneybethlehem.com/",
    "address": "20 W 4th St, Bethlehem, PA 18015",
    "street": "20 W 4th St",
    "city": "Bethlehem",
    "state": "Pennsylvania",
    "zip": "18015",
    "rating": 4,
    "reviews": 116,
    "hours": "{\"Monday\": [\"11AM-6PM\"], \"Tuesday\": [\"11AM-6PM\"], \"Wednesday\": [\"11AM-6PM\"], \"Thursday\": [\"11AM-6PM\"], \"Friday\": [\"11AM-6PM\"], \"Saturday\": [\"11AM-6PM\"], \"Sunday\": [\"Closed\"]}",
    "latitude": 40.610203,
    "longitude": -75.3791844,
    "placeId": "ChIJvTr1WFw-xIkRjGcPSzUhdPU",
    "googleMapsUrl": null
  },
  {
    "slug": "stefko-cash-for-gold-paying-up-to-95-market-value-for-gold-silver",
    "citySlug": "bethlehem",
    "name": "STEFKO CASH FOR GOLD PAYING UP TO 95% MARKET VALUE FOR GOLD & SILVER",
    "phone": "+1 610-419-9888",
    "website": "http://www.stefkocashforgold.com/",
    "address": "1459 Stefko Blvd, Bethlehem, PA 18017",
    "street": "1459 Stefko Blvd",
    "city": "Bethlehem",
    "state": "Pennsylvania",
    "zip": "18017",
    "rating": 5,
    "reviews": 118,
    "hours": "{\"Monday\": [\"10AM-6PM\"], \"Tuesday\": [\"10AM-6PM\"], \"Wednesday\": [\"10AM-6PM\"], \"Thursday\": [\"10AM-6PM\"], \"Friday\": [\"10AM-6PM\"], \"Saturday\": [\"10AM-4PM\"], \"Sunday\": [\"Closed\"]}",
    "latitude": 40.6341963,
    "longitude": -75.35220369999999,
    "placeId": "ChIJH55vsNo_xIkRpNcoGJHroBU",
    "googleMapsUrl": null
  },
  {
    "slug": "easton-exchange",
    "citySlug": "easton",
    "name": "Easton Exchange",
    "phone": "+1 610-515-0520",
    "website": null,
    "address": "58 Centre Sq Cir, Easton, PA 18042",
    "street": "58 Centre Sq Cir",
    "city": "Easton",
    "state": "Pennsylvania",
    "zip": "18042",
    "rating": 4.6,
    "reviews": 219,
    "hours": "{\"Monday\": [\"10AM-6PM\"], \"Tuesday\": [\"10AM-6PM\"], \"Wednesday\": [\"10AM-6PM\"], \"Thursday\": [\"10AM-6PM\"], \"Friday\": [\"10AM-6PM\"], \"Saturday\": [\"10AM-5PM\"], \"Sunday\": [\"Closed\"]}",
    "latitude": 40.6916889,
    "longitude": -75.208877,
    "placeId": "ChIJQZecoFFsxIkRosmJlKNleQg",
    "googleMapsUrl": null
  },
  {
    "slug": "two-rivers-trading-post",
    "citySlug": "easton",
    "name": "Two Rivers Trading Post",
    "phone": "+1 610-252-8855",
    "website": "http://2riverstradingpost.com/",
    "address": "50 Centre Sq Cir, Easton, PA 18042",
    "street": "50 Centre Sq Cir",
    "city": "Easton",
    "state": "Pennsylvania",
    "zip": "18042",
    "rating": 2.5,
    "reviews": 31,
    "hours": null,
    "latitude": 40.6917218,
    "longitude": -75.2095188,
    "placeId": "ChIJE6IPB1FsxIkRUuLaecDOO-w",
    "googleMapsUrl": null
  },
  {
    "slug": "jts-swap-shop",
    "citySlug": "somerset",
    "name": "JT's Swap & Shop",
    "phone": "+1 814-445-7184",
    "website": null,
    "address": "118 W Main St, Somerset, PA 15501",
    "street": "118 W Main St",
    "city": "Somerset",
    "state": "Pennsylvania",
    "zip": "15501",
    "rating": 4.2,
    "reviews": 43,
    "hours": "{\"Monday\": [\"10AM-5PM\"], \"Tuesday\": [\"10AM-5PM\"], \"Wednesday\": [\"10AM-4PM\"], \"Thursday\": [\"10AM-5PM\"], \"Friday\": [\"10AM-5PM\"], \"Saturday\": [\"12AM-4PM\"], \"Sunday\": [\"Closed\"]}",
    "latitude": 40.00853559999999,
    "longitude": -79.0793429,
    "placeId": "ChIJq0ko-ETcyokRH2Ju2Yotqr0",
    "googleMapsUrl": null
  },
  {
    "slug": "got-it-all",
    "citySlug": "glassport",
    "name": "Got It All",
    "phone": "+1 412-696-8823",
    "website": null,
    "address": "606 Monongahela Ave, Glassport, PA 15045",
    "street": "606 Monongahela Ave",
    "city": "Glassport",
    "state": "Pennsylvania",
    "zip": "15045",
    "rating": 3.4,
    "reviews": 5,
    "hours": null,
    "latitude": 40.3256518,
    "longitude": -79.8927136,
    "placeId": "ChIJj49xCLTlNIgRru3ZHkNaS8Y",
    "googleMapsUrl": null
  },
  {
    "slug": "king-gold-exchange",
    "citySlug": "kingston",
    "name": "King Gold Exchange",
    "phone": "+1 570-287-1300",
    "website": "http://www.kgegold.com/",
    "address": "226 Wyoming Ave, Kingston, PA 18704",
    "street": "226 Wyoming Ave",
    "city": "Kingston",
    "state": "Pennsylvania",
    "zip": "18704",
    "rating": 5,
    "reviews": 37,
    "hours": "{\"Monday\": [\"10AM-5PM\"], \"Tuesday\": [\"10AM-5PM\"], \"Wednesday\": [\"10AM-5PM\"], \"Thursday\": [\"10AM-5PM\"], \"Friday\": [\"10AM-5PM\"], \"Saturday\": [\"10AM-2PM\"], \"Sunday\": [\"Closed\"]}",
    "latitude": 41.2624579,
    "longitude": -75.8968012,
    "placeId": "ChIJ87s8MnQaxYkRqKfO9gavDVg",
    "googleMapsUrl": null
  },
  {
    "slug": "pawn-shop",
    "citySlug": "hazleton",
    "name": "Pawn shop",
    "phone": "+1 570-433-1939",
    "website": null,
    "address": "799 N Vine St, Hazleton, PA 18201",
    "street": "799 N Vine St",
    "city": "Hazleton",
    "state": "Pennsylvania",
    "zip": "18201",
    "rating": 4.4,
    "reviews": 90,
    "hours": "{\"Monday\": [\"9AM-8PM\"], \"Tuesday\": [\"10AM-6:30PM\"], \"Wednesday\": [\"9AM-8PM\"], \"Thursday\": [\"9AM-8PM\"], \"Friday\": [\"9AM-8PM\"], \"Saturday\": [\"9AM-8PM\"], \"Sunday\": [\"10AM-6PM\"]}",
    "latitude": 40.9678166,
    "longitude": -75.9781692,
    "placeId": "ChIJ94wcBhGkxYkRNfRHyXyBNbI",
    "googleMapsUrl": null
  },
  {
    "slug": "ocean-gold",
    "citySlug": "nanticoke",
    "name": "Ocean Gold",
    "phone": "+1 570-239-7644",
    "website": null,
    "address": "206 E Main St, Nanticoke, PA 18634",
    "street": "206 E Main St",
    "city": "Nanticoke",
    "state": "Pennsylvania",
    "zip": "18634",
    "rating": 2.1,
    "reviews": 9,
    "hours": null,
    "latitude": 41.2057724,
    "longitude": -76.001503,
    "placeId": "ChIJ-Q--1OUNxYkRJeLiWEUXeKQ",
    "googleMapsUrl": null
  },
  {
    "slug": "american-gold-buying-inc",
    "citySlug": "dallas",
    "name": "American Gold Buying Inc",
    "phone": "+1 570-674-7677",
    "website": null,
    "address": "65 Tunkhannock Hwy, Dallas, PA 18612",
    "street": "65 Tunkhannock Hwy",
    "city": "Dallas",
    "state": "Pennsylvania",
    "zip": "18612",
    "rating": 4.8,
    "reviews": 4,
    "hours": "{\"Monday\": [\"Closed\"], \"Tuesday\": [\"10AM-6PM\"], \"Wednesday\": [\"10AM-6PM\"], \"Thursday\": [\"10AM-6PM\"], \"Friday\": [\"10AM-6PM\"], \"Saturday\": [\"10AM-5PM\"], \"Sunday\": [\"Closed\"]}",
    "latitude": 41.3343144,
    "longitude": -75.95602079999999,
    "placeId": "ChIJpTRD1FcWxYkRcKDkU_aUjYo",
    "googleMapsUrl": null
  },
  {
    "slug": "manolos-pawn-shop",
    "citySlug": "hazleton",
    "name": "Manolo's Pawn Shop",
    "phone": "+1 570-450-5008",
    "website": null,
    "address": "35 E Diamond Ave, Hazleton, PA 18201",
    "street": "35 E Diamond Ave",
    "city": "Hazleton",
    "state": "Pennsylvania",
    "zip": "18201",
    "rating": 3,
    "reviews": 52,
    "hours": "{\"Monday\": [\"9AM-9PM\"], \"Tuesday\": [\"9AM-9PM\"], \"Wednesday\": [\"9AM-9PM\"], \"Thursday\": [\"9AM-9PM\"], \"Friday\": [\"9AM-9PM\"], \"Saturday\": [\"9AM-9PM\"], \"Sunday\": [\"Closed\"]}",
    "latitude": 40.9609357,
    "longitude": -75.9699265,
    "placeId": "ChIJfeNfCzmkxYkReTAH_zZZviw",
    "googleMapsUrl": null
  },
  {
    "slug": "cash-trading-inc",
    "citySlug": "pottsville",
    "name": "Cash & Trading Inc",
    "phone": "+1 570-622-2500",
    "website": null,
    "address": "16 N Centre St, Pottsville, PA 17901",
    "street": "16 N Centre St",
    "city": "Pottsville",
    "state": "Pennsylvania",
    "zip": "17901",
    "rating": 3.7,
    "reviews": 55,
    "hours": "{\"Monday\": [\"10:30AM-6PM\"], \"Tuesday\": [\"10:30AM-6PM\"], \"Wednesday\": [\"10:30AM-6PM\"], \"Thursday\": [\"10:30AM-6PM\"], \"Friday\": [\"10:30AM-6PM\"], \"Saturday\": [\"10:30AM-4PM\"], \"Sunday\": [\"Closed\"]}",
    "latitude": 40.6856313,
    "longitude": -76.19515539999999,
    "placeId": "ChIJqQ9RtqbuxYkRiGZzNPn42cc",
    "googleMapsUrl": null
  },
  {
    "slug": "national-jewelry-and-pawn",
    "citySlug": "lebanon",
    "name": "National Jewelry and Pawn",
    "phone": "+1 717-454-0047",
    "website": "https://www.nationaljewelryandpawn.com/",
    "address": "15 N 9th St, Lebanon, PA 17046",
    "street": "15 N 9th St",
    "city": "Lebanon",
    "state": "Pennsylvania",
    "zip": "17046",
    "rating": 4.2,
    "reviews": 85,
    "hours": "{\"Monday\": [\"9:30AM-5PM\"], \"Tuesday\": [\"9:30AM-5PM\"], \"Wednesday\": [\"9:30AM-5PM\"], \"Thursday\": [\"9:30AM-5PM\"], \"Friday\": [\"9:30AM-5PM\"], \"Saturday\": [\"9:30AM-5PM\"], \"Sunday\": [\"Closed\"]}",
    "latitude": 40.3396441,
    "longitude": -76.4266669,
    "placeId": "ChIJ7TXnm-kCxokRdaC178ZqHSI",
    "googleMapsUrl": null
  },
  {
    "slug": "barkenz-gold-and-jewelry-exchange",
    "citySlug": "beaver-falls",
    "name": "Barkenz Gold and Jewelry Exchange",
    "phone": "+1 724-891-8110",
    "website": null,
    "address": "1020 7th Ave, Beaver Falls, PA 15010",
    "street": "1020 7th Ave",
    "city": "Beaver Falls",
    "state": "Pennsylvania",
    "zip": "15010",
    "rating": 2.3,
    "reviews": 23,
    "hours": "{\"Monday\": [\"10:30AM-5:30PM\"], \"Tuesday\": [\"10:30AM-5:30PM\"], \"Wednesday\": [\"10:30AM-5:30PM\"], \"Thursday\": [\"10:30AM-5:30PM\"], \"Friday\": [\"10:30AM-5:30PM\"], \"Saturday\": [\"Closed\"], \"Sunday\": [\"Closed\"]}",
    "latitude": 40.751643,
    "longitude": -80.3191483,
    "placeId": "ChIJXw2-EFVwNIgRQHmhq08d8jI",
    "googleMapsUrl": null
  },
  {
    "slug": "aston-pawn-shop",
    "citySlug": "aston",
    "name": "Aston Pawn Shop",
    "phone": "+1 610-494-5775",
    "website": "http://www.astonpawn.com/",
    "address": "4716 Pennell Rd, Aston Township, PA 19014",
    "street": "4716 Pennell Rd",
    "city": "Aston",
    "state": "Pennsylvania",
    "zip": "19014",
    "rating": 4.6,
    "reviews": 80,
    "hours": "{\"Monday\": [\"11AM-6PM\"], \"Tuesday\": [\"11AM-5PM\"], \"Wednesday\": [\"11AM-5PM\"], \"Thursday\": [\"11AM-5PM\"], \"Friday\": [\"11AM-6PM\"], \"Saturday\": [\"Closed\"], \"Sunday\": [\"Closed\"]}",
    "latitude": 39.859261,
    "longitude": -75.4266416,
    "placeId": "ChIJXyeJ5w7mxokRhmO0cuGpl3g",
    "googleMapsUrl": null
  },
  {
    "slug": "johns-pawnshop",
    "citySlug": "hazleton",
    "name": "John's Pawnshop",
    "phone": null,
    "website": null,
    "address": "570 Alter St, Hazleton, PA 18201",
    "street": "570 Alter St",
    "city": "Hazleton",
    "state": "Pennsylvania",
    "zip": "18201",
    "rating": 3.4,
    "reviews": 15,
    "hours": null,
    "latitude": 40.9613929,
    "longitude": -75.9783228,
    "placeId": "ChIJY9Jo2BKkxYkRRWqMUvrKnCA",
    "googleMapsUrl": null
  },
  {
    "slug": "pawn-plus",
    "citySlug": "york",
    "name": "Pawn Plus",
    "phone": "+1 717-812-8800",
    "website": "http://www.pawnplus.com/pawn-loans-in-york-pa/",
    "address": "123 W Market St, York, PA 17401",
    "street": "123 W Market St",
    "city": "York",
    "state": "Pennsylvania",
    "zip": "17401",
    "rating": 4.1,
    "reviews": 191,
    "hours": "{\"Monday\": [\"9:30AM-5PM\"], \"Tuesday\": [\"Closed\"], \"Wednesday\": [\"9:30AM-5PM\"], \"Thursday\": [\"9:30AM-5PM\"], \"Friday\": [\"9:30AM-5PM\"], \"Saturday\": [\"9:30AM-5PM\"], \"Sunday\": [\"Closed\"]}",
    "latitude": 39.9617567,
    "longitude": -76.7304494,
    "placeId": "ChIJrTaNNKaOyIkRD8BYihjK5M0",
    "googleMapsUrl": null
  },
  {
    "slug": "sharon-gold-coin-exchange",
    "citySlug": "sharon",
    "name": "Sharon Gold & Coin Exchange",
    "phone": "+1 724-308-7239",
    "website": null,
    "address": "141 E State St, Sharon, PA 16146",
    "street": "141 E State St",
    "city": "Sharon",
    "state": "Pennsylvania",
    "zip": "16146",
    "rating": 4.1,
    "reviews": 14,
    "hours": "{\"Monday\": [\"10AM-5PM\"], \"Tuesday\": [\"10AM-5PM\"], \"Wednesday\": [\"10AM-5PM\"], \"Thursday\": [\"10AM-5PM\"], \"Friday\": [\"10AM-5PM\"], \"Saturday\": [\"10AM-3PM\"], \"Sunday\": [\"Closed\"]}",
    "latitude": 41.2331539,
    "longitude": -80.5065212,
    "placeId": "ChIJUYqlwbbBM4gR1DaFIfCb3CI",
    "googleMapsUrl": null
  },
  {
    "slug": "jp-pawn-shop",
    "citySlug": "hazleton",
    "name": "JP Pawn Shop",
    "phone": "+1 570-401-3979",
    "website": null,
    "address": "45 E Broad St, Hazleton, PA 18201",
    "street": "45 E Broad St",
    "city": "Hazleton",
    "state": "Pennsylvania",
    "zip": "18201",
    "rating": 3.3,
    "reviews": 18,
    "hours": "{\"Monday\": [\"10AM-7PM\"], \"Tuesday\": [\"10AM-7PM\"], \"Wednesday\": [\"10AM-7PM\"], \"Thursday\": [\"10AM-7PM\"], \"Friday\": [\"10AM-7PM\"], \"Saturday\": [\"10AM-7PM\"], \"Sunday\": [\"Closed\"]}",
    "latitude": 40.9537598,
    "longitude": -75.9726061,
    "placeId": "ChIJ2-B7o2mkxYkR9HyFXJmW7io",
    "googleMapsUrl": null
  },
  {
    "slug": "american-cash-traders",
    "citySlug": "coatesville",
    "name": "American Cash Traders",
    "phone": "+1 610-383-7111",
    "website": null,
    "address": "2350 Lincoln Hwy, Coatesville, PA 19320",
    "street": "2350 Lincoln Hwy",
    "city": "Coatesville",
    "state": "Pennsylvania",
    "zip": "19320",
    "rating": 3.5,
    "reviews": 43,
    "hours": "{\"Monday\": [\"10AM-6PM\"], \"Tuesday\": [\"10AM-6PM\"], \"Wednesday\": [\"10AM-6PM\"], \"Thursday\": [\"10AM-6PM\"], \"Friday\": [\"10AM-6PM\"], \"Saturday\": [\"10AM-4PM\"], \"Sunday\": [\"Closed\"]}",
    "latitude": 39.9906313,
    "longitude": -75.7772789,
    "placeId": "ChIJK_Fn2zZZxokREOo7k86xORQ",
    "googleMapsUrl": null
  },
  {
    "slug": "shai-town-cash-for-gold",
    "citySlug": "brookhaven",
    "name": "Shai town cash for gold",
    "phone": "+1 484-768-6911",
    "website": "https://shaitowncashgold.com/",
    "address": "4100 Edgmont Ave Unite E, Brookhaven, PA 19015",
    "street": "4100 Edgmont Ave Unite E",
    "city": "Brookhaven",
    "state": "Pennsylvania",
    "zip": "19015",
    "rating": 4.9,
    "reviews": 89,
    "hours": "{\"Monday\": [\"9AM-5PM\"], \"Tuesday\": [\"9AM-5PM\"], \"Wednesday\": [\"9AM-5PM\"], \"Thursday\": [\"9AM-5PM\"], \"Friday\": [\"9AM-5PM\"], \"Saturday\": [\"Closed\"], \"Sunday\": [\"10AM-5PM\"]}",
    "latitude": 39.8727557,
    "longitude": -75.3888996,
    "placeId": "ChIJt-qPZ9TpxokRQlQLqoZU-Rg",
    "googleMapsUrl": null
  },
  {
    "slug": "compact-disc-outlet",
    "citySlug": "norwood",
    "name": "COMPACT DISC OUTLET",
    "phone": "+1 610-532-3333",
    "website": "http://www.cdoutlet.com/",
    "address": "500 Chester Pike, Norwood, PA 19074",
    "street": "500 Chester Pike",
    "city": "Norwood",
    "state": "Pennsylvania",
    "zip": "19074",
    "rating": 4,
    "reviews": 121,
    "hours": "{\"Monday\": [\"Closed\"], \"Tuesday\": [\"Closed\"], \"Wednesday\": [\"Closed\"], \"Thursday\": [\"Closed\"], \"Friday\": [\"11AM-4PM\"], \"Saturday\": [\"11AM-4PM\"], \"Sunday\": [\"Closed\"]}",
    "latitude": 39.888545,
    "longitude": -75.29956299999999,
    "placeId": "ChIJNaK3iPzCxokRmyTWpWLQmac",
    "googleMapsUrl": null
  },
  {
    "slug": "ez-cash-buy-sell-trade",
    "citySlug": "washington",
    "name": "EZ Cash Buy Sell Trade",
    "phone": "+1 724-222-4499",
    "website": null,
    "address": "1255 W Chestnut St, Washington, PA 15301",
    "street": "1255 W Chestnut St",
    "city": "Washington",
    "state": "Pennsylvania",
    "zip": "15301",
    "rating": 4.8,
    "reviews": 198,
    "hours": "{\"Monday\": [\"10AM-5PM\"], \"Tuesday\": [\"10AM-5PM\"], \"Wednesday\": [\"10AM-5PM\"], \"Thursday\": [\"10AM-5PM\"], \"Friday\": [\"10AM-5PM\"], \"Saturday\": [\"10AM-4PM\"], \"Sunday\": [\"Closed\"]}",
    "latitude": 40.1662538,
    "longitude": -80.27044029999999,
    "placeId": "ChIJG5vwi6WtNYgRvgO0lgJsqzA",
    "googleMapsUrl": null
  },
  {
    "slug": "adams-cash-for-gold",
    "citySlug": "hatboro",
    "name": "Adam's Cash for Gold",
    "phone": "+1 215-550-3641",
    "website": "http://adamscashforgold.com/",
    "address": "21 S York Rd, Hatboro, PA 19040",
    "street": "21 S York Rd",
    "city": "Hatboro",
    "state": "Pennsylvania",
    "zip": "19040",
    "rating": 4.8,
    "reviews": 70,
    "hours": "{\"Monday\": [\"11AM-4PM\"], \"Tuesday\": [\"11AM-4PM\"], \"Wednesday\": [\"11AM-4PM\"], \"Thursday\": [\"11AM-4PM\"], \"Friday\": [\"11AM-4PM\"], \"Saturday\": [\"11AM-2:30PM\"], \"Sunday\": [\"Closed\"]}",
    "latitude": 40.1766167,
    "longitude": -75.10623149999999,
    "placeId": "ChIJiUCebkuuxokRvIiCwTG0YXE",
    "googleMapsUrl": null
  },
  {
    "slug": "pawn-shop-watches-etc",
    "citySlug": "philadelphia",
    "name": "PAWN SHOP - Watches Etc",
    "phone": "+1 215-739-7296",
    "website": "https://www.ebay.com/str/knabazar",
    "address": "3140 Kensington Ave, Philadelphia, PA 19134",
    "street": "3140 Kensington Ave",
    "city": "Philadelphia",
    "state": "Pennsylvania",
    "zip": "19134",
    "rating": 3.2,
    "reviews": 38,
    "hours": "{\"Monday\": [\"8AM-5PM\"], \"Tuesday\": [\"8AM-5PM\"], \"Wednesday\": [\"8AM-5PM\"], \"Thursday\": [\"8AM-5PM\"], \"Friday\": [\"8AM-5PM\"], \"Saturday\": [\"8AM-5PM\"], \"Sunday\": [\"Closed\"]}",
    "latitude": 39.9960184,
    "longitude": -75.1145794,
    "placeId": "ChIJrXjjkda3xokRIKNtvCOsiXc",
    "googleMapsUrl": null
  },
  {
    "slug": "pawn-shop",
    "citySlug": "philadelphia",
    "name": "Pawn Shop",
    "phone": null,
    "website": null,
    "address": "5249 Frankford Ave, Philadelphia, PA 19124",
    "street": "5249 Frankford Ave",
    "city": "Philadelphia",
    "state": "Pennsylvania",
    "zip": "19124",
    "rating": 4.6,
    "reviews": 9,
    "hours": "{\"Monday\": [\"10AM-5PM\"], \"Tuesday\": [\"10AM-5PM\"], \"Wednesday\": [\"10AM-5PM\"], \"Thursday\": [\"10AM-5PM\"], \"Friday\": [\"10AM-5PM\"], \"Saturday\": [\"Closed\"], \"Sunday\": [\"Closed\"]}",
    "latitude": 40.0230188,
    "longitude": -75.07698309999999,
    "placeId": "ChIJKzU1CmS2xokRWvQtAwIEeoE",
    "googleMapsUrl": null
  },
  {
    "slug": "quick-cash-trading-post",
    "citySlug": "levittown",
    "name": "Quick Cash Trading Post",
    "phone": "+1 215-486-7095",
    "website": "http://www.quickcashtradingpost.com/",
    "address": "4534 New Falls Rd, Levittown, PA 19056",
    "street": "4534 New Falls Rd",
    "city": "Levittown",
    "state": "Pennsylvania",
    "zip": "19056",
    "rating": 3.2,
    "reviews": 38,
    "hours": "{\"Monday\": [\"10AM-5PM\"], \"Tuesday\": [\"10AM-5PM\"], \"Wednesday\": [\"10AM-5PM\"], \"Thursday\": [\"10AM-5PM\"], \"Friday\": [\"10AM-5PM\"], \"Saturday\": [\"10AM-5PM\"], \"Sunday\": [\"10AM-3PM\"]}",
    "latitude": 40.136512,
    "longitude": -74.88076509999999,
    "placeId": "ChIJa5ek7htSwYkRaaOawSkJ7og",
    "googleMapsUrl": null
  },
  {
    "slug": "bm-gold-buyers-cash-for-gold",
    "citySlug": "philadelphia",
    "name": "B.M Gold Buyers Cash For Gold",
    "phone": "+1 267-905-5413",
    "website": null,
    "address": "5400 N 5th St, Philadelphia, PA 19120",
    "street": "5400 N 5th St",
    "city": "Philadelphia",
    "state": "Pennsylvania",
    "zip": "19120",
    "rating": 4.7,
    "reviews": 106,
    "hours": "{\"Monday\": [\"9AM-7PM\"], \"Tuesday\": [\"9AM-7PM\"], \"Wednesday\": [\"9AM-7PM\"], \"Thursday\": [\"9AM-7PM\"], \"Friday\": [\"9AM-7PM\"], \"Saturday\": [\"9AM-7PM\"], \"Sunday\": [\"Closed\"]}",
    "latitude": 40.0335627,
    "longitude": -75.1315395,
    "placeId": "ChIJ-_OYip-3xokRkK72MlrR0CQ",
    "googleMapsUrl": null
  },
  {
    "slug": "cash-town",
    "citySlug": "pittsburgh",
    "name": "Cash Town",
    "phone": "+1 412-473-0111",
    "website": null,
    "address": "10716 Frankstown Rd, Pittsburgh, PA 15235",
    "street": "10716 Frankstown Rd",
    "city": "Pittsburgh",
    "state": "Pennsylvania",
    "zip": "15235",
    "rating": 4.1,
    "reviews": 9,
    "hours": "{\"Monday\": [\"10AM-5PM\"], \"Tuesday\": [\"10AM-5PM\"], \"Wednesday\": [\"10AM-5PM\"], \"Thursday\": [\"10AM-5PM\"], \"Friday\": [\"10AM-5PM\"], \"Saturday\": [\"10AM-4PM\"], \"Sunday\": [\"Closed\"]}",
    "latitude": 40.4613665,
    "longitude": -79.840661,
    "placeId": "ChIJoYrtTGXsNIgRgsAWsxs3_rE",
    "googleMapsUrl": null
  },
  {
    "slug": "exton-gold-buyers",
    "citySlug": "exton",
    "name": "Exton Gold Buyers",
    "phone": "+1 484-319-7257",
    "website": "http://www.extongoldbuyers.com/",
    "address": "19341 Pennsylvania, Exton, Exton Square Mall",
    "street": "Exton Square Mall",
    "city": "Exton",
    "state": "Pennsylvania",
    "zip": "19341",
    "rating": 4.6,
    "reviews": 41,
    "hours": "{\"Monday\": [\"10AM-4:30PM\"], \"Tuesday\": [\"10AM-4:30PM\"], \"Wednesday\": [\"10AM-4:30PM\"], \"Thursday\": [\"10AM-4:30PM\"], \"Friday\": [\"10AM-4:30PM\"], \"Saturday\": [\"Closed\"], \"Sunday\": [\"Closed\"]}",
    "latitude": 40.0311694,
    "longitude": -75.62425929999999,
    "placeId": "ChIJR4DFUZz0xokRy_wuU2JDf8M",
    "googleMapsUrl": null
  },
  {
    "slug": "phoenixville-gold-buyers",
    "citySlug": "phoenixville",
    "name": "Phoenixville Gold Buyers",
    "phone": "+1 484-320-0989",
    "website": "http://www.phoenixvillegoldbuyers.com/",
    "address": "135 Nutt Rd, Phoenixville, PA 19460",
    "street": "135 Nutt Rd",
    "city": "Phoenixville",
    "state": "Pennsylvania",
    "zip": "19460",
    "rating": 4.9,
    "reviews": 54,
    "hours": "{\"Monday\": [\"9:30AM-5PM\"], \"Tuesday\": [\"9:30AM-5PM\"], \"Wednesday\": [\"9:30AM-5PM\"], \"Thursday\": [\"9:30AM-5PM\"], \"Friday\": [\"9:30AM-5PM\"], \"Saturday\": [\"Closed\"], \"Sunday\": [\"Closed\"]}",
    "latitude": 40.1242498,
    "longitude": -75.5144747,
    "placeId": "ChIJm7soYR2SxokRefVYfzTdd9E",
    "googleMapsUrl": null
  },
  {
    "slug": "cash4goldtroopercom",
    "citySlug": "norristown",
    "name": "Cash4GoldTrooper.com",
    "phone": "+1 267-975-6331",
    "website": "https://www.cash4goldtrooper.com/",
    "address": "452 Egypt Rd, Norristown, PA 19403",
    "street": "452 Egypt Rd",
    "city": "Norristown",
    "state": "Pennsylvania",
    "zip": "19403",
    "rating": 4.3,
    "reviews": 3,
    "hours": "{\"Monday\": [\"9:30AM-6:30PM\"], \"Tuesday\": [\"9:30AM-6:30PM\"], \"Wednesday\": [\"9:30AM-6:30PM\"], \"Thursday\": [\"9:30AM-6:30PM\"], \"Friday\": [\"9:30AM-6:30PM\"], \"Saturday\": [\"10:30AM-4:30PM\"], \"Sunday\": [\"Closed\"]}",
    "latitude": 40.1305562,
    "longitude": -75.40122699999999,
    "placeId": "ChIJu3n5CLiXxokRChAhwOMf2ws",
    "googleMapsUrl": null
  },
  {
    "slug": "american-cash-traders",
    "citySlug": "pottstown",
    "name": "American Cash Traders",
    "phone": "+1 610-705-0304",
    "website": null,
    "address": "232 E High St, Pottstown, PA 19464",
    "street": "232 E High St",
    "city": "Pottstown",
    "state": "Pennsylvania",
    "zip": "19464",
    "rating": 3.5,
    "reviews": 52,
    "hours": "{\"Monday\": [\"10AM-6PM\"], \"Tuesday\": [\"10AM-6PM\"], \"Wednesday\": [\"10AM-6PM\"], \"Thursday\": [\"10AM-6PM\"], \"Friday\": [\"10AM-6PM\"], \"Saturday\": [\"10AM-4PM\"], \"Sunday\": [\"Closed\"]}",
    "latitude": 40.2453692,
    "longitude": -75.6492143,
    "placeId": "ChIJFWz8L0GGxokR3ZxIWF8maPY",
    "googleMapsUrl": null
  },
  {
    "slug": "cash-flow-tire-auto",
    "citySlug": "pittsburgh",
    "name": "Cash Flow Tire & Auto",
    "phone": "+1 412-853-5787",
    "website": null,
    "address": "1015 Swissvale ave Wilkinsburgh, Pittsburgh, PA 15221",
    "street": "1015 Swissvale ave Wilkinsburgh",
    "city": "Pittsburgh",
    "state": "Pennsylvania",
    "zip": "15221",
    "rating": 4,
    "reviews": 104,
    "hours": "{\"Monday\": [\"9:30AM-6PM\"], \"Tuesday\": [\"9:30AM-6PM\"], \"Wednesday\": [\"9:30AM-6PM\"], \"Thursday\": [\"9:30AM-6PM\"], \"Friday\": [\"9:30AM-6PM\"], \"Saturday\": [\"9:30AM-6PM\"], \"Sunday\": [\"Closed\"]}",
    "latitude": 40.4419794,
    "longitude": -79.87774929999999,
    "placeId": "ChIJO3NKN9LtNIgRz1aKBMkZpzs",
    "googleMapsUrl": null
  },
  {
    "slug": "lowills-jewelers-associates-ltd",
    "citySlug": "philadelphia",
    "name": "Lowill's Jewelers Associates, LTD",
    "phone": "+1 215-844-2225",
    "website": "http://lowillsjewelers.com/%3Futm_source%3Dgmb%26utm_medium%3Dreferral",
    "address": "5719 Germantown Ave, Philadelphia, PA 19144",
    "street": "5719 Germantown Ave",
    "city": "Philadelphia",
    "state": "Pennsylvania",
    "zip": "19144",
    "rating": 4.4,
    "reviews": 34,
    "hours": "{\"Monday\": [\"9AM-5PM\"], \"Tuesday\": [\"9AM-5PM\"], \"Wednesday\": [\"9AM-5PM\"], \"Thursday\": [\"10AM-6PM\"], \"Friday\": [\"9AM-6PM\"], \"Saturday\": [\"10AM-5PM\"], \"Sunday\": [\"Closed\"]}",
    "latitude": 40.0364846,
    "longitude": -75.1751462,
    "placeId": "ChIJs8oW0zW4xokRq0gbjZUBB4g",
    "googleMapsUrl": null
  },
  {
    "slug": "j-r-check-cashing-agency",
    "citySlug": "philadelphia",
    "name": "J & R Check Cashing Agency",
    "phone": "+1 215-856-3922",
    "website": null,
    "address": "3800 Kensington Ave, Philadelphia, PA 19124",
    "street": "3800 Kensington Ave",
    "city": "Philadelphia",
    "state": "Pennsylvania",
    "zip": "19124",
    "rating": 3.2,
    "reviews": 13,
    "hours": "{\"Monday\": [\"9AM-5PM\"], \"Tuesday\": [\"9AM-5PM\"], \"Wednesday\": [\"9AM-5PM\"], \"Thursday\": [\"9AM-5PM\"], \"Friday\": [\"9AM-5PM\"], \"Saturday\": [\"Closed\"], \"Sunday\": [\"Closed\"]}",
    "latitude": 40.0045056,
    "longitude": -75.0991633,
    "placeId": "ChIJuYkDHjG2xokRoBBcU1TEsg4",
    "googleMapsUrl": null
  },
  {
    "slug": "bobs-check-cashing-pawn-shp",
    "citySlug": "philadelphia",
    "name": "Bob's Check Cashing & Pawn Shp",
    "phone": "+1 215-423-2420",
    "website": null,
    "address": "2777 Kensington Ave, Philadelphia, PA 19134",
    "street": "2777 Kensington Ave",
    "city": "Philadelphia",
    "state": "Pennsylvania",
    "zip": "19134",
    "rating": 3.5,
    "reviews": 29,
    "hours": "{\"Monday\": [\"9AM-6PM\"], \"Tuesday\": [\"9AM-6PM\"], \"Wednesday\": [\"9AM-6PM\"], \"Thursday\": [\"9AM-6PM\"], \"Friday\": [\"9AM-6PM\"], \"Saturday\": [\"9AM-3PM\"], \"Sunday\": [\"Closed\"]}",
    "latitude": 39.9912232,
    "longitude": -75.1227104,
    "placeId": "ChIJx40C-SbIxokRlGg_bowXX6A",
    "googleMapsUrl": null
  },
  {
    "slug": "cash-for-gold",
    "citySlug": "belle-vernon",
    "name": "Cash For Gold",
    "phone": null,
    "website": null,
    "address": "417 Don St, Belle Vernon, PA 15012",
    "street": "417 Don St",
    "city": "Belle Vernon",
    "state": "Pennsylvania",
    "zip": "15012",
    "rating": 3.5,
    "reviews": 8,
    "hours": null,
    "latitude": 40.1337185,
    "longitude": -79.85376649999999,
    "placeId": "ChIJff0QNEccNYgRjhJV0oC5Ics",
    "googleMapsUrl": null
  },
  {
    "slug": "olney-pawnbrokers-inc",
    "citySlug": "philadelphia",
    "name": "Olney Pawnbrokers Inc",
    "phone": "+1 215-224-2792",
    "website": "http://olneypawn.com/",
    "address": "5706 N Broad St, Philadelphia, PA 19141",
    "street": "5706 N Broad St",
    "city": "Philadelphia",
    "state": "Pennsylvania",
    "zip": "19141",
    "rating": 2.6,
    "reviews": 21,
    "hours": null,
    "latitude": 40.0401527,
    "longitude": -75.1448242,
    "placeId": "ChIJqxwmtHm3xokR0Mvq9xOxi_o",
    "googleMapsUrl": null
  },
  {
    "slug": "hunting-park-check-cashing-auto-tags",
    "citySlug": "philadelphia",
    "name": "Hunting Park Check Cashing & Auto Tags",
    "phone": "+1 215-223-1350",
    "website": null,
    "address": "2204 W Erie Ave, Philadelphia, PA 19140",
    "street": "2204 W Erie Ave",
    "city": "Philadelphia",
    "state": "Pennsylvania",
    "zip": "19140",
    "rating": 4.7,
    "reviews": 114,
    "hours": "{\"Monday\": [\"9AM-5PM\"], \"Tuesday\": [\"9AM-5PM\"], \"Wednesday\": [\"9AM-5PM\"], \"Thursday\": [\"9AM-5PM\"], \"Friday\": [\"9AM-5:30PM\"], \"Saturday\": [\"9AM-3:30PM\"], \"Sunday\": [\"Closed\"]}",
    "latitude": 40.0107214,
    "longitude": -75.1645604,
    "placeId": "ChIJ4V-uwRq4xokR8WjW6VqXaJ8",
    "googleMapsUrl": null
  }
]